<annotationInfo>
<annotationInfo>
<item  id="10" filename="fyp/MA_UNITDATAX_STATUS_indication.c" linenumber="13" name="icmp_ln13" contextFuncName="ma_unitdatax_status_indication" moduleName="ma_unitdatax_status_" rtlName="icmp_ln13_fu_34_p2" latency="0" BRAM="-1" DSP="-1" FF="0" LUT="9" fileDirectory="E:\FYP\HLS\MAC_SAP"&gt;&lt;\/item&gt;
<item  id="13" filename="fyp/MA_UNITDATAX_STATUS_indication.c" linenumber="15" name="icmp_ln15" contextFuncName="ma_unitdatax_status_indication" moduleName="ma_unitdatax_status_" rtlName="icmp_ln15_fu_40_p2" latency="0" BRAM="-1" DSP="-1" FF="0" LUT="9" fileDirectory="E:\FYP\HLS\MAC_SAP"&gt;&lt;\/item&gt;
<item  id="16" filename="fyp/MA_UNITDATAX_STATUS_indication.c" linenumber="17" name="icmp_ln17" contextFuncName="ma_unitdatax_status_indication" moduleName="ma_unitdatax_status_" rtlName="icmp_ln17_fu_46_p2" latency="0" BRAM="-1" DSP="-1" FF="0" LUT="9" fileDirectory="E:\FYP\HLS\MAC_SAP"&gt;&lt;\/item&gt;
<item  id="19" filename="fyp/MA_UNITDATAX_STATUS_indication.c" linenumber="19" name="icmp_ln19" contextFuncName="ma_unitdatax_status_indication" moduleName="ma_unitdatax_status_" rtlName="icmp_ln19_fu_52_p2" latency="0" BRAM="-1" DSP="-1" FF="0" LUT="9" fileDirectory="E:\FYP\HLS\MAC_SAP"&gt;&lt;\/item&gt;
<item  id="22" filename="fyp/MA_UNITDATAX_STATUS_indication.c" linenumber="21" name="icmp_ln21" contextFuncName="ma_unitdatax_status_indication" moduleName="ma_unitdatax_status_" rtlName="icmp_ln21_fu_58_p2" latency="0" BRAM="-1" DSP="-1" FF="0" LUT="9" fileDirectory="E:\FYP\HLS\MAC_SAP"&gt;&lt;\/item&gt;
<item  id="26" filename="fyp/MA_UNITDATAX_STATUS_indication.c" linenumber="24" name="add_ln24" contextFuncName="ma_unitdatax_status_indication" moduleName="ma_unitdatax_status_" rtlName="add_ln24_fu_68_p2" latency="0" BRAM="-1" DSP="-1" FF="0" LUT="15" fileDirectory="E:\FYP\HLS\MAC_SAP"&gt;&lt;\/item&gt;
<item  id="31" filename="fyp/MA_UNITDATAX_STATUS_indication.c" linenumber="22" name="add_ln22" contextFuncName="ma_unitdatax_status_indication" moduleName="ma_unitdatax_status_" rtlName="add_ln22_fu_84_p2" latency="0" BRAM="-1" DSP="-1" FF="0" LUT="15" fileDirectory="E:\FYP\HLS\MAC_SAP"&gt;&lt;\/item&gt;
<item  id="38" filename="fyp/MA_UNITDATAX_STATUS_indication.c" linenumber="20" name="add_ln20" contextFuncName="ma_unitdatax_status_indication" moduleName="ma_unitdatax_status_" rtlName="add_ln20_fu_100_p2" latency="0" BRAM="-1" DSP="-1" FF="0" LUT="15" fileDirectory="E:\FYP\HLS\MAC_SAP"&gt;&lt;\/item&gt;
<item  id="45" filename="fyp/MA_UNITDATAX_STATUS_indication.c" linenumber="18" name="add_ln18" contextFuncName="ma_unitdatax_status_indication" moduleName="ma_unitdatax_status_" rtlName="add_ln18_fu_116_p2" latency="0" BRAM="-1" DSP="-1" FF="0" LUT="15" fileDirectory="E:\FYP\HLS\MAC_SAP"&gt;&lt;\/item&gt;
<item  id="52" filename="fyp/MA_UNITDATAX_STATUS_indication.c" linenumber="16" name="add_ln16" contextFuncName="ma_unitdatax_status_indication" moduleName="ma_unitdatax_status_" rtlName="add_ln16_fu_132_p2" latency="0" BRAM="-1" DSP="-1" FF="0" LUT="15" fileDirectory="E:\FYP\HLS\MAC_SAP"&gt;&lt;\/item&gt;
<item  id="59" filename="fyp/MA_UNITDATAX_STATUS_indication.c" linenumber="14" name="add_ln14" contextFuncName="ma_unitdatax_status_indication" moduleName="ma_unitdatax_status_" rtlName="add_ln14_fu_148_p2" latency="0" BRAM="-1" DSP="-1" FF="0" LUT="15" fileDirectory="E:\FYP\HLS\MAC_SAP"&gt;&lt;\/item&gt;
&lt;\/annotationInfo&gt;
<annotationInfo>
<item  id="64" filename="fyp/compose_mac_frame.c" linenumber="43" name="seq_num_l" contextFuncName="compose_mac_header" moduleName="compose_mac_frame" rtlName="seq_num_l_fu_553_p1" latency="0" BRAM="-1" DSP="-1" FF="-1" LUT="-1" fileDirectory="E:\FYP\HLS\MAC_SAP"&gt;&lt;\/item&gt;
<item  id="65" filename="fyp/compose_mac_frame.c" linenumber="44" name="tmp" contextFuncName="compose_mac_header" moduleName="compose_mac_frame" rtlName="tmp_fu_558_p4" latency="0" BRAM="-1" DSP="-1" FF="-1" LUT="-1" fileDirectory="E:\FYP\HLS\MAC_SAP"&gt;&lt;\/item&gt;
<item  id="66" filename="fyp/compose_mac_frame.c" linenumber="44" name="seq_num_h" contextFuncName="compose_mac_header" moduleName="compose_mac_frame" rtlName="seq_num_h_fu_568_p1" latency="0" BRAM="-1" DSP="-1" FF="-1" LUT="-1" fileDirectory="E:\FYP\HLS\MAC_SAP"&gt;&lt;\/item&gt;
<item  id="71" filename="fyp/compose_mac_frame.c" linenumber="50" name="trunc_ln50" contextFuncName="compose_mac_header" moduleName="compose_mac_frame" rtlName="trunc_ln50_fu_573_p1" latency="0" BRAM="-1" DSP="-1" FF="-1" LUT="-1" fileDirectory="E:\FYP\HLS\MAC_SAP"&gt;&lt;\/item&gt;
<item  id="72" filename="fyp/compose_mac_frame.c" linenumber="50" name="qos_h" contextFuncName="compose_mac_header" moduleName="compose_mac_frame" rtlName="qos_h_fu_577_p3" latency="0" BRAM="-1" DSP="-1" FF="-1" LUT="-1" fileDirectory="E:\FYP\HLS\MAC_SAP"&gt;&lt;\/item&gt;
<item  id="73" filename="fyp/compose_mac_frame.c" linenumber="51" name="qos_h_1" contextFuncName="compose_mac_header" moduleName="compose_mac_frame" rtlName="qos_h_1_fu_585_p2" latency="0" BRAM="-1" DSP="-1" FF="0" LUT="7" fileDirectory="E:\FYP\HLS\MAC_SAP"&gt;&lt;\/item&gt;
<item  id="74" filename="fyp/compose_mac_frame.c" linenumber="51" name="zext_ln51" contextFuncName="compose_mac_header" moduleName="compose_mac_frame" rtlName="zext_ln51_fu_591_p1" latency="0" BRAM="-1" DSP="-1" FF="-1" LUT="-1" fileDirectory="E:\FYP\HLS\MAC_SAP"&gt;&lt;\/item&gt;
<item  id="82" filename="fyp/compose_mac_frame.c" linenumber="66" name="icmp_ln66" contextFuncName="compose_mac_frame" moduleName="compose_mac_frame" rtlName="icmp_ln66_fu_596_p2" latency="0" BRAM="-1" DSP="-1" FF="0" LUT="11" fileDirectory="E:\FYP\HLS\MAC_SAP"&gt;&lt;\/item&gt;
<item  id="84" filename="fyp/compose_mac_frame.c" linenumber="66" name="j" contextFuncName="compose_mac_frame" moduleName="compose_mac_frame" rtlName="j_fu_602_p2" latency="0" BRAM="-1" DSP="-1" FF="0" LUT="15" fileDirectory="E:\FYP\HLS\MAC_SAP"&gt;&lt;\/item&gt;
<item  id="87" filename="fyp/compose_mac_frame.c" linenumber="67" name="zext_ln67" contextFuncName="compose_mac_frame" moduleName="compose_mac_frame" rtlName="zext_ln67_fu_608_p1" latency="0" BRAM="-1" DSP="-1" FF="-1" LUT="-1" fileDirectory="E:\FYP\HLS\MAC_SAP"&gt;&lt;\/item&gt;
<item  id="90" filename="fyp/compose_mac_frame.c" linenumber="67" name="add_ln67" contextFuncName="compose_mac_frame" moduleName="compose_mac_frame" rtlName="add_ln67_fu_618_p2" latency="0" BRAM="-1" DSP="-1" FF="0" LUT="15" fileDirectory="E:\FYP\HLS\MAC_SAP"&gt;&lt;\/item&gt;
<item  id="91" filename="fyp/compose_mac_frame.c" linenumber="67" name="zext_ln67_1" contextFuncName="compose_mac_frame" moduleName="compose_mac_frame" rtlName="zext_ln67_1_fu_624_p1" latency="0" BRAM="-1" DSP="-1" FF="-1" LUT="-1" fileDirectory="E:\FYP\HLS\MAC_SAP"&gt;&lt;\/item&gt;
<item  id="101" filename="fyp/crc_32.c" linenumber="8" name="icmp_ln8" contextFuncName="calc_crc" moduleName="compose_mac_frame" rtlName="icmp_ln8_fu_629_p2" latency="0" BRAM="-1" DSP="-1" FF="0" LUT="11" fileDirectory="E:\FYP\HLS\MAC_SAP"&gt;&lt;\/item&gt;
<item  id="103" filename="fyp/crc_32.c" linenumber="8" name="i" contextFuncName="calc_crc" moduleName="compose_mac_frame" rtlName="i_fu_635_p2" latency="0" BRAM="-1" DSP="-1" FF="0" LUT="15" fileDirectory="E:\FYP\HLS\MAC_SAP"&gt;&lt;\/item&gt;
<item  id="109" filename="fyp/crc_32.c" linenumber="9" name="zext_ln9" contextFuncName="calc_crc" moduleName="compose_mac_frame" rtlName="zext_ln9_fu_641_p1" latency="0" BRAM="-1" DSP="-1" FF="-1" LUT="-1" fileDirectory="E:\FYP\HLS\MAC_SAP"&gt;&lt;\/item&gt;
<item  id="112" filename="fyp/crc_32.c" linenumber="10" name="shl_ln" contextFuncName="calc_crc" moduleName="compose_mac_frame" rtlName="shl_ln_fu_652_p3" latency="0" BRAM="-1" DSP="-1" FF="-1" LUT="-1" fileDirectory="E:\FYP\HLS\MAC_SAP"&gt;&lt;\/item&gt;
<item  id="113" filename="fyp/crc_32.c" linenumber="10" name="remainder" contextFuncName="calc_crc" moduleName="compose_mac_frame" rtlName="remainder_fu_660_p2" latency="0" BRAM="-1" DSP="-1" FF="0" LUT="32" fileDirectory="E:\FYP\HLS\MAC_SAP"&gt;&lt;\/item&gt;
<item  id="118" filename="fyp/crc_32.c" linenumber="11" name="icmp_ln11" contextFuncName="calc_crc" moduleName="compose_mac_frame" rtlName="icmp_ln11_fu_671_p2" latency="0" BRAM="-1" DSP="-1" FF="0" LUT="11" fileDirectory="E:\FYP\HLS\MAC_SAP"&gt;&lt;\/item&gt;
<item  id="120" filename="fyp/crc_32.c" linenumber="11" name="j_1" contextFuncName="calc_crc" moduleName="compose_mac_frame" rtlName="j_1_fu_677_p2" latency="0" BRAM="-1" DSP="-1" FF="0" LUT="13" fileDirectory="E:\FYP\HLS\MAC_SAP"&gt;&lt;\/item&gt;
<item  id="125" filename="fyp/crc_32.c" linenumber="12" name="tmp_10" contextFuncName="calc_crc" moduleName="compose_mac_frame" rtlName="tmp_10_fu_683_p3" latency="0" BRAM="-1" DSP="-1" FF="-1" LUT="-1" fileDirectory="E:\FYP\HLS\MAC_SAP"&gt;&lt;\/item&gt;
<item  id="126" filename="fyp/crc_32.c" linenumber="13" name="remainder_1" contextFuncName="calc_crc" moduleName="compose_mac_frame" rtlName="remainder_1_fu_691_p2" latency="0" BRAM="-1" DSP="-1" FF="-1" LUT="-1" fileDirectory="E:\FYP\HLS\MAC_SAP"&gt;&lt;\/item&gt;
<item  id="127" filename="fyp/crc_32.c" linenumber="13" name="remainder_2" contextFuncName="calc_crc" moduleName="compose_mac_frame" rtlName="remainder_2_fu_697_p2" latency="0" BRAM="-1" DSP="-1" FF="0" LUT="32" fileDirectory="E:\FYP\HLS\MAC_SAP"&gt;&lt;\/item&gt;
<item  id="128" filename="fyp/crc_32.c" linenumber="12" name="remainder_3" contextFuncName="calc_crc" moduleName="compose_mac_frame" rtlName="remainder_3_fu_703_p3" latency="0" BRAM="-1" DSP="-1" FF="0" LUT="32" fileDirectory="E:\FYP\HLS\MAC_SAP"&gt;&lt;\/item&gt;
<item  id="136" filename="fyp/compose_mac_frame.c" linenumber="71" name="crc_1" contextFuncName="compose_mac_frame" moduleName="compose_mac_frame" rtlName="crc_1_fu_646_p2" latency="0" BRAM="-1" DSP="-1" FF="0" LUT="32" fileDirectory="E:\FYP\HLS\MAC_SAP"&gt;&lt;\/item&gt;
<item  id="140" filename="fyp/compose_mac_frame.c" linenumber="73" name="zext_ln73" contextFuncName="compose_mac_frame" moduleName="compose_mac_frame" rtlName="zext_ln73_fu_716_p1" latency="0" BRAM="-1" DSP="-1" FF="-1" LUT="-1" fileDirectory="E:\FYP\HLS\MAC_SAP"&gt;&lt;\/item&gt;
<item  id="141" filename="fyp/compose_mac_frame.c" linenumber="73" name="icmp_ln73" contextFuncName="compose_mac_frame" moduleName="compose_mac_frame" rtlName="icmp_ln73_fu_720_p2" latency="0" BRAM="-1" DSP="-1" FF="0" LUT="9" fileDirectory="E:\FYP\HLS\MAC_SAP"&gt;&lt;\/item&gt;
<item  id="143" filename="fyp/compose_mac_frame.c" linenumber="73" name="k" contextFuncName="compose_mac_frame" moduleName="compose_mac_frame" rtlName="k_fu_726_p2" latency="0" BRAM="-1" DSP="-1" FF="0" LUT="12" fileDirectory="E:\FYP\HLS\MAC_SAP"&gt;&lt;\/item&gt;
<item  id="146" filename="fyp/compose_mac_frame.c" linenumber="74" name="trunc_ln74" contextFuncName="compose_mac_frame" moduleName="compose_mac_frame" rtlName="trunc_ln74_fu_732_p1" latency="0" BRAM="-1" DSP="-1" FF="-1" LUT="-1" fileDirectory="E:\FYP\HLS\MAC_SAP"&gt;&lt;\/item&gt;
<item  id="147" filename="fyp/compose_mac_frame.c" linenumber="74" name="shl_ln1" contextFuncName="compose_mac_frame" moduleName="compose_mac_frame" rtlName="shl_ln1_fu_736_p3" latency="0" BRAM="-1" DSP="-1" FF="-1" LUT="-1" fileDirectory="E:\FYP\HLS\MAC_SAP"&gt;&lt;\/item&gt;
<item  id="148" filename="fyp/compose_mac_frame.c" linenumber="74" name="zext_ln74_1" contextFuncName="compose_mac_frame" moduleName="compose_mac_frame" rtlName="zext_ln74_1_fu_744_p1" latency="0" BRAM="-1" DSP="-1" FF="-1" LUT="-1" fileDirectory="E:\FYP\HLS\MAC_SAP"&gt;&lt;\/item&gt;
<item  id="149" filename="fyp/compose_mac_frame.c" linenumber="74" name="lshr_ln74" contextFuncName="compose_mac_frame" moduleName="compose_mac_frame" rtlName="lshr_ln74_fu_748_p2" latency="0" BRAM="-1" DSP="-1" FF="0" LUT="101" fileDirectory="E:\FYP\HLS\MAC_SAP"&gt;&lt;\/item&gt;
<item  id="150" filename="fyp/compose_mac_frame.c" linenumber="74" name="trunc_ln74_1" contextFuncName="compose_mac_frame" moduleName="compose_mac_frame" rtlName="trunc_ln74_1_fu_753_p1" latency="0" BRAM="-1" DSP="-1" FF="-1" LUT="-1" fileDirectory="E:\FYP\HLS\MAC_SAP"&gt;&lt;\/item&gt;
<item  id="151" filename="fyp/compose_mac_frame.c" linenumber="74" name="sub_ln74" contextFuncName="compose_mac_frame" moduleName="compose_mac_frame" rtlName="sub_ln74_fu_758_p2" latency="0" BRAM="-1" DSP="-1" FF="0" LUT="15" fileDirectory="E:\FYP\HLS\MAC_SAP"&gt;&lt;\/item&gt;
<item  id="152" filename="fyp/compose_mac_frame.c" linenumber="74" name="sext_ln74" contextFuncName="compose_mac_frame" moduleName="compose_mac_frame" rtlName="sext_ln74_fu_764_p1" latency="0" BRAM="-1" DSP="-1" FF="-1" LUT="-1" fileDirectory="E:\FYP\HLS\MAC_SAP"&gt;&lt;\/item&gt;
<item  id="153" filename="fyp/compose_mac_frame.c" linenumber="74" name="zext_ln74" contextFuncName="compose_mac_frame" moduleName="compose_mac_frame" rtlName="zext_ln74_fu_768_p1" latency="0" BRAM="-1" DSP="-1" FF="-1" LUT="-1" fileDirectory="E:\FYP\HLS\MAC_SAP"&gt;&lt;\/item&gt;
&lt;\/annotationInfo&gt;
<annotationInfo>
<item  id="32" filename="fyp/edca.c" linenumber="53" name="icmp_ln53" contextFuncName="enqueue_dequeue_frame" moduleName="enqueue_dequeue_fram" rtlName="grp_fu_420_p2" latency="0" BRAM="-1" DSP="-1" FF="0" LUT="8" fileDirectory="E:\FYP\HLS\MAC_SAP"&gt;&lt;\/item&gt;
<item  id="35" filename="fyp/edca.c" linenumber="66" name="icmp_ln66" contextFuncName="enqueue_dequeue_frame" moduleName="enqueue_dequeue_fram" rtlName="grp_fu_426_p2" latency="0" BRAM="-1" DSP="-1" FF="0" LUT="8" fileDirectory="E:\FYP\HLS\MAC_SAP"&gt;&lt;\/item&gt;
<item  id="38" filename="fyp/edca.c" linenumber="79" name="icmp_ln79" contextFuncName="enqueue_dequeue_frame" moduleName="enqueue_dequeue_fram" rtlName="grp_fu_432_p2" latency="0" BRAM="-1" DSP="-1" FF="0" LUT="9" fileDirectory="E:\FYP\HLS\MAC_SAP"&gt;&lt;\/item&gt;
<item  id="41" filename="fyp/edca.c" linenumber="92" name="icmp_ln92" contextFuncName="enqueue_dequeue_frame" moduleName="enqueue_dequeue_fram" rtlName="grp_fu_438_p2" latency="0" BRAM="-1" DSP="-1" FF="0" LUT="8" fileDirectory="E:\FYP\HLS\MAC_SAP"&gt;&lt;\/item&gt;
<item  id="44" filename="fyp/edca.c" linenumber="93" name="icmp_ln93" contextFuncName="enqueue_dequeue_frame" moduleName="enqueue_dequeue_fram" rtlName="icmp_ln93_fu_476_p2" latency="0" BRAM="-1" DSP="-1" FF="0" LUT="9" fileDirectory="E:\FYP\HLS\MAC_SAP"&gt;&lt;\/item&gt;
<item  id="47" filename="fyp/edca.c" linenumber="97" name="zext_ln97" contextFuncName="enqueue_dequeue_frame" moduleName="enqueue_dequeue_fram" rtlName="mul_ln97_fu_486_p00" latency="0" BRAM="-1" DSP="-1" FF="-1" LUT="-1" fileDirectory="E:\FYP\HLS\MAC_SAP"&gt;&lt;\/item&gt;
<item  id="48" filename="fyp/edca.c" linenumber="97" name="mul_ln97" contextFuncName="enqueue_dequeue_frame" moduleName="enqueue_dequeue_fram" rtlName="mul_ln97_fu_486_p2" latency="0" BRAM="-1" DSP="0" FF="0" LUT="33" fileDirectory="E:\FYP\HLS\MAC_SAP"&gt;&lt;\/item&gt;
<item  id="52" filename="fyp/edca.c" linenumber="96" name="zext_ln96" contextFuncName="enqueue_dequeue_frame" moduleName="enqueue_dequeue_fram" rtlName="zext_ln96_fu_620_p1" latency="0" BRAM="-1" DSP="-1" FF="-1" LUT="-1" fileDirectory="E:\FYP\HLS\MAC_SAP"&gt;&lt;\/item&gt;
<item  id="53" filename="fyp/edca.c" linenumber="96" name="icmp_ln96" contextFuncName="enqueue_dequeue_frame" moduleName="enqueue_dequeue_fram" rtlName="icmp_ln96_fu_624_p2" latency="0" BRAM="-1" DSP="-1" FF="0" LUT="11" fileDirectory="E:\FYP\HLS\MAC_SAP"&gt;&lt;\/item&gt;
<item  id="55" filename="fyp/edca.c" linenumber="96" name="vo_1" contextFuncName="enqueue_dequeue_frame" moduleName="enqueue_dequeue_fram" rtlName="vo_1_fu_630_p2" latency="0" BRAM="-1" DSP="-1" FF="0" LUT="15" fileDirectory="E:\FYP\HLS\MAC_SAP"&gt;&lt;\/item&gt;
<item  id="59" filename="fyp/edca.c" linenumber="97" name="zext_ln97_1" contextFuncName="enqueue_dequeue_frame" moduleName="enqueue_dequeue_fram" rtlName="zext_ln97_1_fu_636_p1" latency="0" BRAM="-1" DSP="-1" FF="-1" LUT="-1" fileDirectory="E:\FYP\HLS\MAC_SAP"&gt;&lt;\/item&gt;
<item  id="62" filename="fyp/edca.c" linenumber="97" name="add_ln97" contextFuncName="enqueue_dequeue_frame" moduleName="enqueue_dequeue_fram" rtlName="add_ln97_fu_641_p2" latency="0" BRAM="-1" DSP="-1" FF="0" LUT="16" fileDirectory="E:\FYP\HLS\MAC_SAP"&gt;&lt;\/item&gt;
<item  id="63" filename="fyp/edca.c" linenumber="97" name="zext_ln97_2" contextFuncName="enqueue_dequeue_frame" moduleName="enqueue_dequeue_fram" rtlName="zext_ln97_2_fu_668_p1" latency="0" BRAM="-1" DSP="-1" FF="-1" LUT="-1" fileDirectory="E:\FYP\HLS\MAC_SAP"&gt;&lt;\/item&gt;
<item  id="64" filename="fyp/edca.c" linenumber="97" name="add_ln97_1" contextFuncName="enqueue_dequeue_frame" moduleName="enqueue_dequeue_fram" rtlName="add_ln97_1_fu_671_p2" latency="0" BRAM="-1" DSP="-1" FF="0" LUT="18" fileDirectory="E:\FYP\HLS\MAC_SAP"&gt;&lt;\/item&gt;
<item  id="65" filename="fyp/edca.c" linenumber="97" name="zext_ln97_3" contextFuncName="enqueue_dequeue_frame" moduleName="enqueue_dequeue_fram" rtlName="zext_ln97_3_fu_677_p1" latency="0" BRAM="-1" DSP="-1" FF="-1" LUT="-1" fileDirectory="E:\FYP\HLS\MAC_SAP"&gt;&lt;\/item&gt;
<item  id="70" filename="fyp/edca.c" linenumber="102" name="add_ln102" contextFuncName="enqueue_dequeue_frame" moduleName="enqueue_dequeue_fram" rtlName="add_ln102_fu_646_p2" latency="0" BRAM="-1" DSP="-1" FF="0" LUT="10" fileDirectory="E:\FYP\HLS\MAC_SAP"&gt;&lt;\/item&gt;
<item  id="72" filename="fyp/edca.c" linenumber="103" name="add_ln103" contextFuncName="enqueue_dequeue_frame" moduleName="enqueue_dequeue_fram" rtlName="add_ln103_fu_657_p2" latency="0" BRAM="-1" DSP="-1" FF="0" LUT="12" fileDirectory="E:\FYP\HLS\MAC_SAP"&gt;&lt;\/item&gt;
<item  id="76" filename="fyp/edca.c" linenumber="80" name="icmp_ln80" contextFuncName="enqueue_dequeue_frame" moduleName="enqueue_dequeue_fram" rtlName="icmp_ln80_fu_492_p2" latency="0" BRAM="-1" DSP="-1" FF="0" LUT="9" fileDirectory="E:\FYP\HLS\MAC_SAP"&gt;&lt;\/item&gt;
<item  id="79" filename="fyp/edca.c" linenumber="84" name="zext_ln84" contextFuncName="enqueue_dequeue_frame" moduleName="enqueue_dequeue_fram" rtlName="mul_ln84_fu_502_p00" latency="0" BRAM="-1" DSP="-1" FF="-1" LUT="-1" fileDirectory="E:\FYP\HLS\MAC_SAP"&gt;&lt;\/item&gt;
<item  id="80" filename="fyp/edca.c" linenumber="84" name="mul_ln84" contextFuncName="enqueue_dequeue_frame" moduleName="enqueue_dequeue_fram" rtlName="mul_ln84_fu_502_p2" latency="0" BRAM="-1" DSP="0" FF="0" LUT="33" fileDirectory="E:\FYP\HLS\MAC_SAP"&gt;&lt;\/item&gt;
<item  id="84" filename="fyp/edca.c" linenumber="83" name="zext_ln83" contextFuncName="enqueue_dequeue_frame" moduleName="enqueue_dequeue_fram" rtlName="zext_ln83_fu_682_p1" latency="0" BRAM="-1" DSP="-1" FF="-1" LUT="-1" fileDirectory="E:\FYP\HLS\MAC_SAP"&gt;&lt;\/item&gt;
<item  id="85" filename="fyp/edca.c" linenumber="83" name="icmp_ln83" contextFuncName="enqueue_dequeue_frame" moduleName="enqueue_dequeue_fram" rtlName="icmp_ln83_fu_686_p2" latency="0" BRAM="-1" DSP="-1" FF="0" LUT="11" fileDirectory="E:\FYP\HLS\MAC_SAP"&gt;&lt;\/item&gt;
<item  id="87" filename="fyp/edca.c" linenumber="83" name="vi_1" contextFuncName="enqueue_dequeue_frame" moduleName="enqueue_dequeue_fram" rtlName="vi_1_fu_692_p2" latency="0" BRAM="-1" DSP="-1" FF="0" LUT="15" fileDirectory="E:\FYP\HLS\MAC_SAP"&gt;&lt;\/item&gt;
<item  id="91" filename="fyp/edca.c" linenumber="84" name="zext_ln84_1" contextFuncName="enqueue_dequeue_frame" moduleName="enqueue_dequeue_fram" rtlName="zext_ln84_1_fu_698_p1" latency="0" BRAM="-1" DSP="-1" FF="-1" LUT="-1" fileDirectory="E:\FYP\HLS\MAC_SAP"&gt;&lt;\/item&gt;
<item  id="94" filename="fyp/edca.c" linenumber="84" name="add_ln84" contextFuncName="enqueue_dequeue_frame" moduleName="enqueue_dequeue_fram" rtlName="add_ln84_fu_703_p2" latency="0" BRAM="-1" DSP="-1" FF="0" LUT="16" fileDirectory="E:\FYP\HLS\MAC_SAP"&gt;&lt;\/item&gt;
<item  id="95" filename="fyp/edca.c" linenumber="84" name="zext_ln84_2" contextFuncName="enqueue_dequeue_frame" moduleName="enqueue_dequeue_fram" rtlName="zext_ln84_2_fu_730_p1" latency="0" BRAM="-1" DSP="-1" FF="-1" LUT="-1" fileDirectory="E:\FYP\HLS\MAC_SAP"&gt;&lt;\/item&gt;
<item  id="96" filename="fyp/edca.c" linenumber="84" name="add_ln84_1" contextFuncName="enqueue_dequeue_frame" moduleName="enqueue_dequeue_fram" rtlName="add_ln84_1_fu_733_p2" latency="0" BRAM="-1" DSP="-1" FF="0" LUT="18" fileDirectory="E:\FYP\HLS\MAC_SAP"&gt;&lt;\/item&gt;
<item  id="97" filename="fyp/edca.c" linenumber="84" name="zext_ln84_3" contextFuncName="enqueue_dequeue_frame" moduleName="enqueue_dequeue_fram" rtlName="zext_ln84_3_fu_739_p1" latency="0" BRAM="-1" DSP="-1" FF="-1" LUT="-1" fileDirectory="E:\FYP\HLS\MAC_SAP"&gt;&lt;\/item&gt;
<item  id="102" filename="fyp/edca.c" linenumber="89" name="add_ln89" contextFuncName="enqueue_dequeue_frame" moduleName="enqueue_dequeue_fram" rtlName="add_ln89_fu_708_p2" latency="0" BRAM="-1" DSP="-1" FF="0" LUT="10" fileDirectory="E:\FYP\HLS\MAC_SAP"&gt;&lt;\/item&gt;
<item  id="104" filename="fyp/edca.c" linenumber="90" name="add_ln90" contextFuncName="enqueue_dequeue_frame" moduleName="enqueue_dequeue_fram" rtlName="add_ln90_fu_719_p2" latency="0" BRAM="-1" DSP="-1" FF="0" LUT="12" fileDirectory="E:\FYP\HLS\MAC_SAP"&gt;&lt;\/item&gt;
<item  id="108" filename="fyp/edca.c" linenumber="67" name="icmp_ln67" contextFuncName="enqueue_dequeue_frame" moduleName="enqueue_dequeue_fram" rtlName="icmp_ln67_fu_508_p2" latency="0" BRAM="-1" DSP="-1" FF="0" LUT="9" fileDirectory="E:\FYP\HLS\MAC_SAP"&gt;&lt;\/item&gt;
<item  id="111" filename="fyp/edca.c" linenumber="71" name="zext_ln71" contextFuncName="enqueue_dequeue_frame" moduleName="enqueue_dequeue_fram" rtlName="mul_ln71_fu_518_p00" latency="0" BRAM="-1" DSP="-1" FF="-1" LUT="-1" fileDirectory="E:\FYP\HLS\MAC_SAP"&gt;&lt;\/item&gt;
<item  id="112" filename="fyp/edca.c" linenumber="71" name="mul_ln71" contextFuncName="enqueue_dequeue_frame" moduleName="enqueue_dequeue_fram" rtlName="mul_ln71_fu_518_p2" latency="0" BRAM="-1" DSP="0" FF="0" LUT="33" fileDirectory="E:\FYP\HLS\MAC_SAP"&gt;&lt;\/item&gt;
<item  id="116" filename="fyp/edca.c" linenumber="70" name="zext_ln70" contextFuncName="enqueue_dequeue_frame" moduleName="enqueue_dequeue_fram" rtlName="zext_ln70_fu_744_p1" latency="0" BRAM="-1" DSP="-1" FF="-1" LUT="-1" fileDirectory="E:\FYP\HLS\MAC_SAP"&gt;&lt;\/item&gt;
<item  id="117" filename="fyp/edca.c" linenumber="70" name="icmp_ln70" contextFuncName="enqueue_dequeue_frame" moduleName="enqueue_dequeue_fram" rtlName="icmp_ln70_fu_748_p2" latency="0" BRAM="-1" DSP="-1" FF="0" LUT="11" fileDirectory="E:\FYP\HLS\MAC_SAP"&gt;&lt;\/item&gt;
<item  id="119" filename="fyp/edca.c" linenumber="70" name="be_1" contextFuncName="enqueue_dequeue_frame" moduleName="enqueue_dequeue_fram" rtlName="be_1_fu_754_p2" latency="0" BRAM="-1" DSP="-1" FF="0" LUT="15" fileDirectory="E:\FYP\HLS\MAC_SAP"&gt;&lt;\/item&gt;
<item  id="123" filename="fyp/edca.c" linenumber="71" name="zext_ln71_1" contextFuncName="enqueue_dequeue_frame" moduleName="enqueue_dequeue_fram" rtlName="zext_ln71_1_fu_760_p1" latency="0" BRAM="-1" DSP="-1" FF="-1" LUT="-1" fileDirectory="E:\FYP\HLS\MAC_SAP"&gt;&lt;\/item&gt;
<item  id="126" filename="fyp/edca.c" linenumber="71" name="add_ln71" contextFuncName="enqueue_dequeue_frame" moduleName="enqueue_dequeue_fram" rtlName="add_ln71_fu_765_p2" latency="0" BRAM="-1" DSP="-1" FF="0" LUT="16" fileDirectory="E:\FYP\HLS\MAC_SAP"&gt;&lt;\/item&gt;
<item  id="127" filename="fyp/edca.c" linenumber="71" name="zext_ln71_2" contextFuncName="enqueue_dequeue_frame" moduleName="enqueue_dequeue_fram" rtlName="zext_ln71_2_fu_792_p1" latency="0" BRAM="-1" DSP="-1" FF="-1" LUT="-1" fileDirectory="E:\FYP\HLS\MAC_SAP"&gt;&lt;\/item&gt;
<item  id="128" filename="fyp/edca.c" linenumber="71" name="add_ln71_1" contextFuncName="enqueue_dequeue_frame" moduleName="enqueue_dequeue_fram" rtlName="add_ln71_1_fu_795_p2" latency="0" BRAM="-1" DSP="-1" FF="0" LUT="17" fileDirectory="E:\FYP\HLS\MAC_SAP"&gt;&lt;\/item&gt;
<item  id="129" filename="fyp/edca.c" linenumber="71" name="zext_ln71_3" contextFuncName="enqueue_dequeue_frame" moduleName="enqueue_dequeue_fram" rtlName="zext_ln71_3_fu_801_p1" latency="0" BRAM="-1" DSP="-1" FF="-1" LUT="-1" fileDirectory="E:\FYP\HLS\MAC_SAP"&gt;&lt;\/item&gt;
<item  id="134" filename="fyp/edca.c" linenumber="76" name="add_ln76" contextFuncName="enqueue_dequeue_frame" moduleName="enqueue_dequeue_fram" rtlName="add_ln76_fu_770_p2" latency="0" BRAM="-1" DSP="-1" FF="0" LUT="10" fileDirectory="E:\FYP\HLS\MAC_SAP"&gt;&lt;\/item&gt;
<item  id="136" filename="fyp/edca.c" linenumber="77" name="add_ln77" contextFuncName="enqueue_dequeue_frame" moduleName="enqueue_dequeue_fram" rtlName="add_ln77_fu_781_p2" latency="0" BRAM="-1" DSP="-1" FF="0" LUT="12" fileDirectory="E:\FYP\HLS\MAC_SAP"&gt;&lt;\/item&gt;
<item  id="140" filename="fyp/edca.c" linenumber="54" name="icmp_ln54" contextFuncName="enqueue_dequeue_frame" moduleName="enqueue_dequeue_fram" rtlName="icmp_ln54_fu_524_p2" latency="0" BRAM="-1" DSP="-1" FF="0" LUT="9" fileDirectory="E:\FYP\HLS\MAC_SAP"&gt;&lt;\/item&gt;
<item  id="143" filename="fyp/edca.c" linenumber="58" name="zext_ln58" contextFuncName="enqueue_dequeue_frame" moduleName="enqueue_dequeue_fram" rtlName="mul_ln58_fu_534_p00" latency="0" BRAM="-1" DSP="-1" FF="-1" LUT="-1" fileDirectory="E:\FYP\HLS\MAC_SAP"&gt;&lt;\/item&gt;
<item  id="144" filename="fyp/edca.c" linenumber="58" name="mul_ln58" contextFuncName="enqueue_dequeue_frame" moduleName="enqueue_dequeue_fram" rtlName="mul_ln58_fu_534_p2" latency="0" BRAM="-1" DSP="0" FF="0" LUT="33" fileDirectory="E:\FYP\HLS\MAC_SAP"&gt;&lt;\/item&gt;
<item  id="148" filename="fyp/edca.c" linenumber="57" name="zext_ln57" contextFuncName="enqueue_dequeue_frame" moduleName="enqueue_dequeue_fram" rtlName="zext_ln57_fu_806_p1" latency="0" BRAM="-1" DSP="-1" FF="-1" LUT="-1" fileDirectory="E:\FYP\HLS\MAC_SAP"&gt;&lt;\/item&gt;
<item  id="149" filename="fyp/edca.c" linenumber="57" name="icmp_ln57" contextFuncName="enqueue_dequeue_frame" moduleName="enqueue_dequeue_fram" rtlName="icmp_ln57_fu_810_p2" latency="0" BRAM="-1" DSP="-1" FF="0" LUT="11" fileDirectory="E:\FYP\HLS\MAC_SAP"&gt;&lt;\/item&gt;
<item  id="151" filename="fyp/edca.c" linenumber="57" name="bk_1" contextFuncName="enqueue_dequeue_frame" moduleName="enqueue_dequeue_fram" rtlName="bk_1_fu_816_p2" latency="0" BRAM="-1" DSP="-1" FF="0" LUT="15" fileDirectory="E:\FYP\HLS\MAC_SAP"&gt;&lt;\/item&gt;
<item  id="155" filename="fyp/edca.c" linenumber="58" name="zext_ln58_1" contextFuncName="enqueue_dequeue_frame" moduleName="enqueue_dequeue_fram" rtlName="zext_ln58_1_fu_822_p1" latency="0" BRAM="-1" DSP="-1" FF="-1" LUT="-1" fileDirectory="E:\FYP\HLS\MAC_SAP"&gt;&lt;\/item&gt;
<item  id="158" filename="fyp/edca.c" linenumber="58" name="add_ln58" contextFuncName="enqueue_dequeue_frame" moduleName="enqueue_dequeue_fram" rtlName="add_ln58_fu_827_p2" latency="0" BRAM="-1" DSP="-1" FF="0" LUT="16" fileDirectory="E:\FYP\HLS\MAC_SAP"&gt;&lt;\/item&gt;
<item  id="159" filename="fyp/edca.c" linenumber="58" name="zext_ln58_2" contextFuncName="enqueue_dequeue_frame" moduleName="enqueue_dequeue_fram" rtlName="zext_ln58_2_fu_854_p1" latency="0" BRAM="-1" DSP="-1" FF="-1" LUT="-1" fileDirectory="E:\FYP\HLS\MAC_SAP"&gt;&lt;\/item&gt;
<item  id="164" filename="fyp/edca.c" linenumber="63" name="add_ln63" contextFuncName="enqueue_dequeue_frame" moduleName="enqueue_dequeue_fram" rtlName="add_ln63_fu_832_p2" latency="0" BRAM="-1" DSP="-1" FF="0" LUT="10" fileDirectory="E:\FYP\HLS\MAC_SAP"&gt;&lt;\/item&gt;
<item  id="166" filename="fyp/edca.c" linenumber="64" name="add_ln64" contextFuncName="enqueue_dequeue_frame" moduleName="enqueue_dequeue_fram" rtlName="add_ln64_fu_843_p2" latency="0" BRAM="-1" DSP="-1" FF="0" LUT="12" fileDirectory="E:\FYP\HLS\MAC_SAP"&gt;&lt;\/item&gt;
<item  id="174" filename="fyp/edca.c" linenumber="109" name="icmp_ln109" contextFuncName="enqueue_dequeue_frame" moduleName="enqueue_dequeue_fram" rtlName="grp_fu_420_p2" latency="0" BRAM="-1" DSP="-1" FF="0" LUT="8" fileDirectory="E:\FYP\HLS\MAC_SAP"&gt;&lt;\/item&gt;
<item  id="177" filename="fyp/edca.c" linenumber="122" name="icmp_ln122" contextFuncName="enqueue_dequeue_frame" moduleName="enqueue_dequeue_fram" rtlName="grp_fu_426_p2" latency="0" BRAM="-1" DSP="-1" FF="0" LUT="8" fileDirectory="E:\FYP\HLS\MAC_SAP"&gt;&lt;\/item&gt;
<item  id="180" filename="fyp/edca.c" linenumber="135" name="icmp_ln135" contextFuncName="enqueue_dequeue_frame" moduleName="enqueue_dequeue_fram" rtlName="grp_fu_432_p2" latency="0" BRAM="-1" DSP="-1" FF="0" LUT="9" fileDirectory="E:\FYP\HLS\MAC_SAP"&gt;&lt;\/item&gt;
<item  id="183" filename="fyp/edca.c" linenumber="148" name="icmp_ln148" contextFuncName="enqueue_dequeue_frame" moduleName="enqueue_dequeue_fram" rtlName="grp_fu_438_p2" latency="0" BRAM="-1" DSP="-1" FF="0" LUT="8" fileDirectory="E:\FYP\HLS\MAC_SAP"&gt;&lt;\/item&gt;
<item  id="186" filename="fyp/edca.c" linenumber="149" name="icmp_ln149" contextFuncName="enqueue_dequeue_frame" moduleName="enqueue_dequeue_fram" rtlName="icmp_ln149_fu_556_p2" latency="0" BRAM="-1" DSP="-1" FF="0" LUT="9" fileDirectory="E:\FYP\HLS\MAC_SAP"&gt;&lt;\/item&gt;
<item  id="189" filename="fyp/edca.c" linenumber="153" name="zext_ln153" contextFuncName="enqueue_dequeue_frame" moduleName="enqueue_dequeue_fram" rtlName="mul_ln153_fu_566_p00" latency="0" BRAM="-1" DSP="-1" FF="-1" LUT="-1" fileDirectory="E:\FYP\HLS\MAC_SAP"&gt;&lt;\/item&gt;
<item  id="190" filename="fyp/edca.c" linenumber="153" name="mul_ln153" contextFuncName="enqueue_dequeue_frame" moduleName="enqueue_dequeue_fram" rtlName="mul_ln153_fu_566_p2" latency="0" BRAM="-1" DSP="0" FF="0" LUT="33" fileDirectory="E:\FYP\HLS\MAC_SAP"&gt;&lt;\/item&gt;
<item  id="194" filename="fyp/edca.c" linenumber="152" name="zext_ln152" contextFuncName="enqueue_dequeue_frame" moduleName="enqueue_dequeue_fram" rtlName="zext_ln152_fu_858_p1" latency="0" BRAM="-1" DSP="-1" FF="-1" LUT="-1" fileDirectory="E:\FYP\HLS\MAC_SAP"&gt;&lt;\/item&gt;
<item  id="195" filename="fyp/edca.c" linenumber="152" name="icmp_ln152" contextFuncName="enqueue_dequeue_frame" moduleName="enqueue_dequeue_fram" rtlName="icmp_ln152_fu_862_p2" latency="0" BRAM="-1" DSP="-1" FF="0" LUT="11" fileDirectory="E:\FYP\HLS\MAC_SAP"&gt;&lt;\/item&gt;
<item  id="197" filename="fyp/edca.c" linenumber="152" name="vo" contextFuncName="enqueue_dequeue_frame" moduleName="enqueue_dequeue_fram" rtlName="vo_fu_868_p2" latency="0" BRAM="-1" DSP="-1" FF="0" LUT="15" fileDirectory="E:\FYP\HLS\MAC_SAP"&gt;&lt;\/item&gt;
<item  id="201" filename="fyp/edca.c" linenumber="153" name="add_ln153" contextFuncName="enqueue_dequeue_frame" moduleName="enqueue_dequeue_fram" rtlName="add_ln153_fu_874_p2" latency="0" BRAM="-1" DSP="-1" FF="0" LUT="16" fileDirectory="E:\FYP\HLS\MAC_SAP"&gt;&lt;\/item&gt;
<item  id="202" filename="fyp/edca.c" linenumber="153" name="zext_ln153_1" contextFuncName="enqueue_dequeue_frame" moduleName="enqueue_dequeue_fram" rtlName="zext_ln153_1_fu_879_p1" latency="0" BRAM="-1" DSP="-1" FF="-1" LUT="-1" fileDirectory="E:\FYP\HLS\MAC_SAP"&gt;&lt;\/item&gt;
<item  id="203" filename="fyp/edca.c" linenumber="153" name="add_ln153_1" contextFuncName="enqueue_dequeue_frame" moduleName="enqueue_dequeue_fram" rtlName="add_ln153_1_fu_883_p2" latency="0" BRAM="-1" DSP="-1" FF="0" LUT="18" fileDirectory="E:\FYP\HLS\MAC_SAP"&gt;&lt;\/item&gt;
<item  id="204" filename="fyp/edca.c" linenumber="153" name="zext_ln153_3" contextFuncName="enqueue_dequeue_frame" moduleName="enqueue_dequeue_fram" rtlName="zext_ln153_3_fu_889_p1" latency="0" BRAM="-1" DSP="-1" FF="-1" LUT="-1" fileDirectory="E:\FYP\HLS\MAC_SAP"&gt;&lt;\/item&gt;
<item  id="207" filename="fyp/edca.c" linenumber="153" name="zext_ln153_2" contextFuncName="enqueue_dequeue_frame" moduleName="enqueue_dequeue_fram" rtlName="zext_ln153_2_fu_916_p1" latency="0" BRAM="-1" DSP="-1" FF="-1" LUT="-1" fileDirectory="E:\FYP\HLS\MAC_SAP"&gt;&lt;\/item&gt;
<item  id="212" filename="fyp/edca.c" linenumber="158" name="add_ln158" contextFuncName="enqueue_dequeue_frame" moduleName="enqueue_dequeue_fram" rtlName="add_ln158_fu_894_p2" latency="0" BRAM="-1" DSP="-1" FF="0" LUT="10" fileDirectory="E:\FYP\HLS\MAC_SAP"&gt;&lt;\/item&gt;
<item  id="214" filename="fyp/edca.c" linenumber="159" name="add_ln159" contextFuncName="enqueue_dequeue_frame" moduleName="enqueue_dequeue_fram" rtlName="add_ln159_fu_905_p2" latency="0" BRAM="-1" DSP="-1" FF="0" LUT="12" fileDirectory="E:\FYP\HLS\MAC_SAP"&gt;&lt;\/item&gt;
<item  id="218" filename="fyp/edca.c" linenumber="136" name="icmp_ln136" contextFuncName="enqueue_dequeue_frame" moduleName="enqueue_dequeue_fram" rtlName="icmp_ln136_fu_572_p2" latency="0" BRAM="-1" DSP="-1" FF="0" LUT="9" fileDirectory="E:\FYP\HLS\MAC_SAP"&gt;&lt;\/item&gt;
<item  id="221" filename="fyp/edca.c" linenumber="140" name="zext_ln140" contextFuncName="enqueue_dequeue_frame" moduleName="enqueue_dequeue_fram" rtlName="mul_ln140_fu_582_p00" latency="0" BRAM="-1" DSP="-1" FF="-1" LUT="-1" fileDirectory="E:\FYP\HLS\MAC_SAP"&gt;&lt;\/item&gt;
<item  id="222" filename="fyp/edca.c" linenumber="140" name="mul_ln140" contextFuncName="enqueue_dequeue_frame" moduleName="enqueue_dequeue_fram" rtlName="mul_ln140_fu_582_p2" latency="0" BRAM="-1" DSP="0" FF="0" LUT="33" fileDirectory="E:\FYP\HLS\MAC_SAP"&gt;&lt;\/item&gt;
<item  id="226" filename="fyp/edca.c" linenumber="139" name="zext_ln139" contextFuncName="enqueue_dequeue_frame" moduleName="enqueue_dequeue_fram" rtlName="zext_ln139_fu_921_p1" latency="0" BRAM="-1" DSP="-1" FF="-1" LUT="-1" fileDirectory="E:\FYP\HLS\MAC_SAP"&gt;&lt;\/item&gt;
<item  id="227" filename="fyp/edca.c" linenumber="139" name="icmp_ln139" contextFuncName="enqueue_dequeue_frame" moduleName="enqueue_dequeue_fram" rtlName="icmp_ln139_fu_925_p2" latency="0" BRAM="-1" DSP="-1" FF="0" LUT="11" fileDirectory="E:\FYP\HLS\MAC_SAP"&gt;&lt;\/item&gt;
<item  id="229" filename="fyp/edca.c" linenumber="139" name="vi" contextFuncName="enqueue_dequeue_frame" moduleName="enqueue_dequeue_fram" rtlName="vi_fu_931_p2" latency="0" BRAM="-1" DSP="-1" FF="0" LUT="15" fileDirectory="E:\FYP\HLS\MAC_SAP"&gt;&lt;\/item&gt;
<item  id="233" filename="fyp/edca.c" linenumber="140" name="add_ln140" contextFuncName="enqueue_dequeue_frame" moduleName="enqueue_dequeue_fram" rtlName="add_ln140_fu_937_p2" latency="0" BRAM="-1" DSP="-1" FF="0" LUT="16" fileDirectory="E:\FYP\HLS\MAC_SAP"&gt;&lt;\/item&gt;
<item  id="234" filename="fyp/edca.c" linenumber="140" name="zext_ln140_1" contextFuncName="enqueue_dequeue_frame" moduleName="enqueue_dequeue_fram" rtlName="zext_ln140_1_fu_942_p1" latency="0" BRAM="-1" DSP="-1" FF="-1" LUT="-1" fileDirectory="E:\FYP\HLS\MAC_SAP"&gt;&lt;\/item&gt;
<item  id="235" filename="fyp/edca.c" linenumber="140" name="add_ln140_1" contextFuncName="enqueue_dequeue_frame" moduleName="enqueue_dequeue_fram" rtlName="add_ln140_1_fu_946_p2" latency="0" BRAM="-1" DSP="-1" FF="0" LUT="18" fileDirectory="E:\FYP\HLS\MAC_SAP"&gt;&lt;\/item&gt;
<item  id="236" filename="fyp/edca.c" linenumber="140" name="zext_ln140_3" contextFuncName="enqueue_dequeue_frame" moduleName="enqueue_dequeue_fram" rtlName="zext_ln140_3_fu_952_p1" latency="0" BRAM="-1" DSP="-1" FF="-1" LUT="-1" fileDirectory="E:\FYP\HLS\MAC_SAP"&gt;&lt;\/item&gt;
<item  id="239" filename="fyp/edca.c" linenumber="140" name="zext_ln140_2" contextFuncName="enqueue_dequeue_frame" moduleName="enqueue_dequeue_fram" rtlName="zext_ln140_2_fu_979_p1" latency="0" BRAM="-1" DSP="-1" FF="-1" LUT="-1" fileDirectory="E:\FYP\HLS\MAC_SAP"&gt;&lt;\/item&gt;
<item  id="244" filename="fyp/edca.c" linenumber="145" name="add_ln145" contextFuncName="enqueue_dequeue_frame" moduleName="enqueue_dequeue_fram" rtlName="add_ln145_fu_957_p2" latency="0" BRAM="-1" DSP="-1" FF="0" LUT="10" fileDirectory="E:\FYP\HLS\MAC_SAP"&gt;&lt;\/item&gt;
<item  id="246" filename="fyp/edca.c" linenumber="146" name="add_ln146" contextFuncName="enqueue_dequeue_frame" moduleName="enqueue_dequeue_fram" rtlName="add_ln146_fu_968_p2" latency="0" BRAM="-1" DSP="-1" FF="0" LUT="12" fileDirectory="E:\FYP\HLS\MAC_SAP"&gt;&lt;\/item&gt;
<item  id="250" filename="fyp/edca.c" linenumber="123" name="icmp_ln123" contextFuncName="enqueue_dequeue_frame" moduleName="enqueue_dequeue_fram" rtlName="icmp_ln123_fu_588_p2" latency="0" BRAM="-1" DSP="-1" FF="0" LUT="9" fileDirectory="E:\FYP\HLS\MAC_SAP"&gt;&lt;\/item&gt;
<item  id="253" filename="fyp/edca.c" linenumber="127" name="zext_ln127" contextFuncName="enqueue_dequeue_frame" moduleName="enqueue_dequeue_fram" rtlName="mul_ln127_fu_598_p00" latency="0" BRAM="-1" DSP="-1" FF="-1" LUT="-1" fileDirectory="E:\FYP\HLS\MAC_SAP"&gt;&lt;\/item&gt;
<item  id="254" filename="fyp/edca.c" linenumber="127" name="mul_ln127" contextFuncName="enqueue_dequeue_frame" moduleName="enqueue_dequeue_fram" rtlName="mul_ln127_fu_598_p2" latency="0" BRAM="-1" DSP="0" FF="0" LUT="33" fileDirectory="E:\FYP\HLS\MAC_SAP"&gt;&lt;\/item&gt;
<item  id="258" filename="fyp/edca.c" linenumber="126" name="zext_ln126" contextFuncName="enqueue_dequeue_frame" moduleName="enqueue_dequeue_fram" rtlName="zext_ln126_fu_984_p1" latency="0" BRAM="-1" DSP="-1" FF="-1" LUT="-1" fileDirectory="E:\FYP\HLS\MAC_SAP"&gt;&lt;\/item&gt;
<item  id="259" filename="fyp/edca.c" linenumber="126" name="icmp_ln126" contextFuncName="enqueue_dequeue_frame" moduleName="enqueue_dequeue_fram" rtlName="icmp_ln126_fu_988_p2" latency="0" BRAM="-1" DSP="-1" FF="0" LUT="11" fileDirectory="E:\FYP\HLS\MAC_SAP"&gt;&lt;\/item&gt;
<item  id="261" filename="fyp/edca.c" linenumber="126" name="be" contextFuncName="enqueue_dequeue_frame" moduleName="enqueue_dequeue_fram" rtlName="be_fu_994_p2" latency="0" BRAM="-1" DSP="-1" FF="0" LUT="15" fileDirectory="E:\FYP\HLS\MAC_SAP"&gt;&lt;\/item&gt;
<item  id="265" filename="fyp/edca.c" linenumber="127" name="add_ln127" contextFuncName="enqueue_dequeue_frame" moduleName="enqueue_dequeue_fram" rtlName="add_ln127_fu_1000_p2" latency="0" BRAM="-1" DSP="-1" FF="0" LUT="16" fileDirectory="E:\FYP\HLS\MAC_SAP"&gt;&lt;\/item&gt;
<item  id="266" filename="fyp/edca.c" linenumber="127" name="zext_ln127_1" contextFuncName="enqueue_dequeue_frame" moduleName="enqueue_dequeue_fram" rtlName="zext_ln127_1_fu_1005_p1" latency="0" BRAM="-1" DSP="-1" FF="-1" LUT="-1" fileDirectory="E:\FYP\HLS\MAC_SAP"&gt;&lt;\/item&gt;
<item  id="267" filename="fyp/edca.c" linenumber="127" name="add_ln127_1" contextFuncName="enqueue_dequeue_frame" moduleName="enqueue_dequeue_fram" rtlName="add_ln127_1_fu_1009_p2" latency="0" BRAM="-1" DSP="-1" FF="0" LUT="17" fileDirectory="E:\FYP\HLS\MAC_SAP"&gt;&lt;\/item&gt;
<item  id="268" filename="fyp/edca.c" linenumber="127" name="zext_ln127_3" contextFuncName="enqueue_dequeue_frame" moduleName="enqueue_dequeue_fram" rtlName="zext_ln127_3_fu_1015_p1" latency="0" BRAM="-1" DSP="-1" FF="-1" LUT="-1" fileDirectory="E:\FYP\HLS\MAC_SAP"&gt;&lt;\/item&gt;
<item  id="271" filename="fyp/edca.c" linenumber="127" name="zext_ln127_2" contextFuncName="enqueue_dequeue_frame" moduleName="enqueue_dequeue_fram" rtlName="zext_ln127_2_fu_1042_p1" latency="0" BRAM="-1" DSP="-1" FF="-1" LUT="-1" fileDirectory="E:\FYP\HLS\MAC_SAP"&gt;&lt;\/item&gt;
<item  id="276" filename="fyp/edca.c" linenumber="132" name="add_ln132" contextFuncName="enqueue_dequeue_frame" moduleName="enqueue_dequeue_fram" rtlName="add_ln132_fu_1020_p2" latency="0" BRAM="-1" DSP="-1" FF="0" LUT="10" fileDirectory="E:\FYP\HLS\MAC_SAP"&gt;&lt;\/item&gt;
<item  id="278" filename="fyp/edca.c" linenumber="133" name="add_ln133" contextFuncName="enqueue_dequeue_frame" moduleName="enqueue_dequeue_fram" rtlName="add_ln133_fu_1031_p2" latency="0" BRAM="-1" DSP="-1" FF="0" LUT="12" fileDirectory="E:\FYP\HLS\MAC_SAP"&gt;&lt;\/item&gt;
<item  id="282" filename="fyp/edca.c" linenumber="110" name="icmp_ln110" contextFuncName="enqueue_dequeue_frame" moduleName="enqueue_dequeue_fram" rtlName="icmp_ln110_fu_604_p2" latency="0" BRAM="-1" DSP="-1" FF="0" LUT="9" fileDirectory="E:\FYP\HLS\MAC_SAP"&gt;&lt;\/item&gt;
<item  id="285" filename="fyp/edca.c" linenumber="114" name="zext_ln114" contextFuncName="enqueue_dequeue_frame" moduleName="enqueue_dequeue_fram" rtlName="mul_ln114_fu_614_p00" latency="0" BRAM="-1" DSP="-1" FF="-1" LUT="-1" fileDirectory="E:\FYP\HLS\MAC_SAP"&gt;&lt;\/item&gt;
<item  id="286" filename="fyp/edca.c" linenumber="114" name="mul_ln114" contextFuncName="enqueue_dequeue_frame" moduleName="enqueue_dequeue_fram" rtlName="mul_ln114_fu_614_p2" latency="0" BRAM="-1" DSP="0" FF="0" LUT="33" fileDirectory="E:\FYP\HLS\MAC_SAP"&gt;&lt;\/item&gt;
<item  id="290" filename="fyp/edca.c" linenumber="113" name="zext_ln113" contextFuncName="enqueue_dequeue_frame" moduleName="enqueue_dequeue_fram" rtlName="zext_ln113_fu_1047_p1" latency="0" BRAM="-1" DSP="-1" FF="-1" LUT="-1" fileDirectory="E:\FYP\HLS\MAC_SAP"&gt;&lt;\/item&gt;
<item  id="291" filename="fyp/edca.c" linenumber="113" name="icmp_ln113" contextFuncName="enqueue_dequeue_frame" moduleName="enqueue_dequeue_fram" rtlName="icmp_ln113_fu_1051_p2" latency="0" BRAM="-1" DSP="-1" FF="0" LUT="11" fileDirectory="E:\FYP\HLS\MAC_SAP"&gt;&lt;\/item&gt;
<item  id="293" filename="fyp/edca.c" linenumber="113" name="bk" contextFuncName="enqueue_dequeue_frame" moduleName="enqueue_dequeue_fram" rtlName="bk_fu_1057_p2" latency="0" BRAM="-1" DSP="-1" FF="0" LUT="15" fileDirectory="E:\FYP\HLS\MAC_SAP"&gt;&lt;\/item&gt;
<item  id="297" filename="fyp/edca.c" linenumber="114" name="add_ln114" contextFuncName="enqueue_dequeue_frame" moduleName="enqueue_dequeue_fram" rtlName="add_ln114_fu_1063_p2" latency="0" BRAM="-1" DSP="-1" FF="0" LUT="16" fileDirectory="E:\FYP\HLS\MAC_SAP"&gt;&lt;\/item&gt;
<item  id="298" filename="fyp/edca.c" linenumber="114" name="zext_ln114_1" contextFuncName="enqueue_dequeue_frame" moduleName="enqueue_dequeue_fram" rtlName="zext_ln114_1_fu_1068_p1" latency="0" BRAM="-1" DSP="-1" FF="-1" LUT="-1" fileDirectory="E:\FYP\HLS\MAC_SAP"&gt;&lt;\/item&gt;
<item  id="301" filename="fyp/edca.c" linenumber="114" name="zext_ln114_2" contextFuncName="enqueue_dequeue_frame" moduleName="enqueue_dequeue_fram" rtlName="zext_ln114_2_fu_1095_p1" latency="0" BRAM="-1" DSP="-1" FF="-1" LUT="-1" fileDirectory="E:\FYP\HLS\MAC_SAP"&gt;&lt;\/item&gt;
<item  id="306" filename="fyp/edca.c" linenumber="119" name="add_ln119" contextFuncName="enqueue_dequeue_frame" moduleName="enqueue_dequeue_fram" rtlName="add_ln119_fu_1073_p2" latency="0" BRAM="-1" DSP="-1" FF="0" LUT="10" fileDirectory="E:\FYP\HLS\MAC_SAP"&gt;&lt;\/item&gt;
<item  id="308" filename="fyp/edca.c" linenumber="120" name="add_ln120" contextFuncName="enqueue_dequeue_frame" moduleName="enqueue_dequeue_fram" rtlName="add_ln120_fu_1084_p2" latency="0" BRAM="-1" DSP="-1" FF="0" LUT="12" fileDirectory="E:\FYP\HLS\MAC_SAP"&gt;&lt;\/item&gt;
&lt;\/annotationInfo&gt;
<annotationInfo>
<item  id="6" filename="fyp/r_n_g.c" linenumber="8" name="low" contextFuncName="random_int_gen" moduleName="random_int_gen" rtlName="low_fu_46_p1" latency="0" BRAM="-1" DSP="-1" FF="-1" LUT="-1" fileDirectory="E:\FYP\HLS\MAC_SAP"&gt;&lt;\/item&gt;
<item  id="7" filename="fyp/r_n_g.c" linenumber="8" name="zext_ln8" contextFuncName="random_int_gen" moduleName="random_int_gen" rtlName="low_1_fu_54_p00" latency="0" BRAM="-1" DSP="-1" FF="-1" LUT="-1" fileDirectory="E:\FYP\HLS\MAC_SAP"&gt;&lt;\/item&gt;
<item  id="9" filename="fyp/r_n_g.c" linenumber="10" name="low_1" contextFuncName="random_int_gen" moduleName="random_int_gen" rtlName="low_1_fu_54_p2" latency="0" BRAM="-1" DSP="1" FF="0" LUT="6" fileDirectory="E:\FYP\HLS\MAC_SAP"&gt;&lt;\/item&gt;
<item  id="12" filename="fyp/r_n_g.c" linenumber="11" name="high" contextFuncName="random_int_gen" moduleName="random_int_gen" rtlName="high_fu_60_p4" latency="0" BRAM="-1" DSP="-1" FF="-1" LUT="-1" fileDirectory="E:\FYP\HLS\MAC_SAP"&gt;&lt;\/item&gt;
<item  id="13" filename="fyp/r_n_g.c" linenumber="11" name="high_1" contextFuncName="random_int_gen" moduleName="random_int_gen" rtlName="high_2_fu_154_p10" latency="0" BRAM="-1" DSP="-1" FF="-1" LUT="-1" fileDirectory="E:\FYP\HLS\MAC_SAP"&gt;&lt;\/item&gt;
<item  id="14" filename="fyp/r_n_g.c" linenumber="12" name="high_2" contextFuncName="random_int_gen" moduleName="random_int_gen" rtlName="send_frame_mul_mucud_U24" latency="0" BRAM="-1" DSP="-1" FF="-1" LUT="-1" fileDirectory="E:\FYP\HLS\MAC_SAP"&gt;&lt;\/item&gt;
<item  id="15" filename="fyp/r_n_g.c" linenumber="12" name="trunc_ln12" contextFuncName="random_int_gen" moduleName="random_int_gen" rtlName="trunc_ln12_fu_83_p1" latency="0" BRAM="-1" DSP="-1" FF="-1" LUT="-1" fileDirectory="E:\FYP\HLS\MAC_SAP"&gt;&lt;\/item&gt;
<item  id="16" filename="fyp/r_n_g.c" linenumber="13" name="zext_ln13" contextFuncName="random_int_gen" moduleName="random_int_gen" rtlName="zext_ln13_fu_86_p1" latency="0" BRAM="-1" DSP="-1" FF="-1" LUT="-1" fileDirectory="E:\FYP\HLS\MAC_SAP"&gt;&lt;\/item&gt;
<item  id="17" filename="fyp/r_n_g.c" linenumber="13" name="trunc_ln1" contextFuncName="random_int_gen" moduleName="random_int_gen" rtlName="trunc_ln1_reg_171" latency="0" BRAM="-1" DSP="-1" FF="-1" LUT="-1" fileDirectory="E:\FYP\HLS\MAC_SAP"&gt;&lt;\/item&gt;
<item  id="18" filename="fyp/r_n_g.c" linenumber="13" name="add_ln13" contextFuncName="random_int_gen" moduleName="random_int_gen" rtlName="add_ln13_fu_90_p2" latency="0" BRAM="-1" DSP="-1" FF="0" LUT="23" fileDirectory="E:\FYP\HLS\MAC_SAP"&gt;&lt;\/item&gt;
<item  id="19" filename="fyp/r_n_g.c" linenumber="13" name="zext_ln13_1" contextFuncName="random_int_gen" moduleName="random_int_gen" rtlName="zext_ln13_1_fu_95_p1" latency="0" BRAM="-1" DSP="-1" FF="-1" LUT="-1" fileDirectory="E:\FYP\HLS\MAC_SAP"&gt;&lt;\/item&gt;
<item  id="20" filename="fyp/r_n_g.c" linenumber="13" name="x" contextFuncName="random_int_gen" moduleName="random_int_gen" rtlName="x_fu_99_p2" latency="0" BRAM="-1" DSP="-1" FF="0" LUT="101" fileDirectory="E:\FYP\HLS\MAC_SAP"&gt;&lt;\/item&gt;
<item  id="21" filename="fyp/r_n_g.c" linenumber="14" name="x_1" contextFuncName="random_int_gen" moduleName="random_int_gen" rtlName="x_1_fu_105_p2" latency="0" BRAM="-1" DSP="-1" FF="0" LUT="39" fileDirectory="E:\FYP\HLS\MAC_SAP"&gt;&lt;\/item&gt;
<item  id="22" filename="fyp/r_n_g.c" linenumber="14" name="trunc_ln14" contextFuncName="random_int_gen" moduleName="random_int_gen" rtlName="trunc_ln14_fu_110_p1" latency="0" BRAM="-1" DSP="-1" FF="-1" LUT="-1" fileDirectory="E:\FYP\HLS\MAC_SAP"&gt;&lt;\/item&gt;
<item  id="23" filename="fyp/r_n_g.c" linenumber="15" name="zext_ln15" contextFuncName="random_int_gen" moduleName="random_int_gen" rtlName="zext_ln15_fu_122_p1" latency="0" BRAM="-1" DSP="-1" FF="-1" LUT="-1" fileDirectory="E:\FYP\HLS\MAC_SAP"&gt;&lt;\/item&gt;
<item  id="24" filename="fyp/r_n_g.c" linenumber="15" name="tmp_1" contextFuncName="random_int_gen" moduleName="random_int_gen" rtlName="tmp_1_reg_181" latency="0" BRAM="-1" DSP="-1" FF="-1" LUT="-1" fileDirectory="E:\FYP\HLS\MAC_SAP"&gt;&lt;\/item&gt;
<item  id="25" filename="fyp/r_n_g.c" linenumber="15" name="zext_ln15_1" contextFuncName="random_int_gen" moduleName="random_int_gen" rtlName="zext_ln15_1_fu_125_p1" latency="0" BRAM="-1" DSP="-1" FF="-1" LUT="-1" fileDirectory="E:\FYP\HLS\MAC_SAP"&gt;&lt;\/item&gt;
<item  id="26" filename="fyp/r_n_g.c" linenumber="15" name="x_2" contextFuncName="random_int_gen" moduleName="random_int_gen" rtlName="x_2_fu_128_p2" latency="0" BRAM="-1" DSP="-1" FF="-1" LUT="-1" fileDirectory="E:\FYP\HLS\MAC_SAP"&gt;&lt;\/item&gt;
<item  id="28" filename="fyp/r_n_g.c" linenumber="17" name="zext_ln17" contextFuncName="random_int_gen" moduleName="random_int_gen" rtlName="grp_fu_144_p10" latency="0" BRAM="-1" DSP="-1" FF="-1" LUT="-1" fileDirectory="E:\FYP\HLS\MAC_SAP"&gt;&lt;\/item&gt;
<item  id="29" filename="fyp/r_n_g.c" linenumber="17" name="urem_ln17" contextFuncName="random_int_gen" moduleName="random_int_gen" rtlName="send_frame_urem_3bkb_U23" latency="35" BRAM="-1" DSP="-1" FF="-1" LUT="-1" fileDirectory="E:\FYP\HLS\MAC_SAP"&gt;&lt;\/item&gt;
<item  id="30" filename="fyp/r_n_g.c" linenumber="17" name="ret_val" contextFuncName="random_int_gen" moduleName="random_int_gen" rtlName="ret_val_fu_150_p1" latency="0" BRAM="-1" DSP="-1" FF="-1" LUT="-1" fileDirectory="E:\FYP\HLS\MAC_SAP"&gt;&lt;\/item&gt;
&lt;\/annotationInfo&gt;
<annotationInfo>
<item  id="52" filename="fyp/MA_UNITDATAX_request.c" linenumber="32" name="llc_data" contextFuncName="ma_unitdatax_request" moduleName="ma_unitdatax_request" rtlName="llc_data_U" latency="0" BRAM="-1" DSP="-1" FF="-1" LUT="-1" fileDirectory="E:\FYP\HLS\MAC_SAP"&gt;&lt;\/item&gt;
<item  id="53" filename="fyp/MA_UNITDATAX_request.c" linenumber="33" name="mac_data" contextFuncName="ma_unitdatax_request" moduleName="ma_unitdatax_request" rtlName="mac_data_U" latency="0" BRAM="-1" DSP="-1" FF="-1" LUT="-1" fileDirectory="E:\FYP\HLS\MAC_SAP"&gt;&lt;\/item&gt;
<item  id="54" filename="fyp/MA_UNITDATAX_request.c" linenumber="15" name="tmp" contextFuncName="ma_unitdatax_request" moduleName="ma_unitdatax_request" rtlName="tmp_reg_641" latency="0" BRAM="-1" DSP="-1" FF="-1" LUT="-1" fileDirectory="E:\FYP\HLS\MAC_SAP"&gt;&lt;\/item&gt;
<item  id="59" filename="fyp/MA_UNITDATAX_request.c" linenumber="20" name="_ln20" contextFuncName="ma_unitdatax_request" moduleName="ma_unitdatax_request" rtlName="grp_ma_unitdatax_status_s_fu_313" latency="0" BRAM="-1" DSP="-1" FF="-1" LUT="-1" fileDirectory="E:\FYP\HLS\MAC_SAP"&gt;&lt;\/item&gt;
<item  id="62" filename="fyp/MA_UNITDATAX_request.c" linenumber="23" name="icmp_ln23" contextFuncName="ma_unitdatax_request" moduleName="ma_unitdatax_request" rtlName="icmp_ln23_fu_361_p2" latency="0" BRAM="-1" DSP="-1" FF="0" LUT="11" fileDirectory="E:\FYP\HLS\MAC_SAP"&gt;&lt;\/item&gt;
<item  id="63" filename="fyp/MA_UNITDATAX_request.c" linenumber="23" name="icmp_ln23_1" contextFuncName="ma_unitdatax_request" moduleName="ma_unitdatax_request" rtlName="icmp_ln23_1_fu_367_p2" latency="0" BRAM="-1" DSP="-1" FF="0" LUT="11" fileDirectory="E:\FYP\HLS\MAC_SAP"&gt;&lt;\/item&gt;
<item  id="64" filename="fyp/MA_UNITDATAX_request.c" linenumber="23" name="and_ln23" contextFuncName="ma_unitdatax_request" moduleName="ma_unitdatax_request" rtlName="and_ln23_fu_373_p2" latency="0" BRAM="-1" DSP="-1" FF="0" LUT="2" fileDirectory="E:\FYP\HLS\MAC_SAP"&gt;&lt;\/item&gt;
<item  id="67" filename="fyp/MA_UNITDATAX_request.c" linenumber="24" name="_ln24" contextFuncName="ma_unitdatax_request" moduleName="ma_unitdatax_request" rtlName="grp_ma_unitdatax_status_s_fu_313" latency="0" BRAM="-1" DSP="-1" FF="-1" LUT="-1" fileDirectory="E:\FYP\HLS\MAC_SAP"&gt;&lt;\/item&gt;
<item  id="97" filename="fyp/MA_UNITDATAX_request.c" linenumber="35" name="icmp_ln35" contextFuncName="ma_unitdatax_request" moduleName="ma_unitdatax_request" rtlName="icmp_ln35_fu_499_p2" latency="0" BRAM="-1" DSP="-1" FF="0" LUT="11" fileDirectory="E:\FYP\HLS\MAC_SAP"&gt;&lt;\/item&gt;
<item  id="99" filename="fyp/MA_UNITDATAX_request.c" linenumber="35" name="i" contextFuncName="ma_unitdatax_request" moduleName="ma_unitdatax_request" rtlName="i_fu_505_p2" latency="0" BRAM="-1" DSP="-1" FF="0" LUT="15" fileDirectory="E:\FYP\HLS\MAC_SAP"&gt;&lt;\/item&gt;
<item  id="102" filename="fyp/MA_UNITDATAX_request.c" linenumber="36" name="zext_ln36" contextFuncName="ma_unitdatax_request" moduleName="ma_unitdatax_request" rtlName="zext_ln36_fu_511_p1" latency="0" BRAM="-1" DSP="-1" FF="-1" LUT="-1" fileDirectory="E:\FYP\HLS\MAC_SAP"&gt;&lt;\/item&gt;
<item  id="110" filename="fyp/MA_UNITDATAX_request.c" linenumber="39" name="_ln39" contextFuncName="ma_unitdatax_request" moduleName="ma_unitdatax_request" rtlName="grp_compose_mac_frame_fu_303" latency="1" BRAM="-1" DSP="-1" FF="-1" LUT="-1" fileDirectory="E:\FYP\HLS\MAC_SAP"&gt;&lt;\/item&gt;
<item  id="111" filename="fyp/MA_UNITDATAX_request.c" linenumber="41" name="add_ln41" contextFuncName="ma_unitdatax_request" moduleName="ma_unitdatax_request" rtlName="add_ln41_fu_521_p2" latency="0" BRAM="-1" DSP="-1" FF="0" LUT="13" fileDirectory="E:\FYP\HLS\MAC_SAP"&gt;&lt;\/item&gt;
<item  id="112" filename="fyp/MA_UNITDATAX_request.c" linenumber="41" name="tmp_5" contextFuncName="ma_unitdatax_request" moduleName="ma_unitdatax_request" rtlName="tmp_5_fu_526_p4" latency="0" BRAM="-1" DSP="-1" FF="-1" LUT="-1" fileDirectory="E:\FYP\HLS\MAC_SAP"&gt;&lt;\/item&gt;
<item  id="113" filename="fyp/MA_UNITDATAX_request.c" linenumber="41" name="icmp_ln41" contextFuncName="ma_unitdatax_request" moduleName="ma_unitdatax_request" rtlName="icmp_ln41_fu_536_p2" latency="0" BRAM="-1" DSP="-1" FF="0" LUT="9" fileDirectory="E:\FYP\HLS\MAC_SAP"&gt;&lt;\/item&gt;
<item  id="121" filename="fyp/MA_UNITDATAX_request.c" linenumber="67" name="trunc_ln67" contextFuncName="ma_unitdatax_request" moduleName="ma_unitdatax_request" rtlName="trunc_ln67_fu_558_p1" latency="0" BRAM="-1" DSP="-1" FF="-1" LUT="-1" fileDirectory="E:\FYP\HLS\MAC_SAP"&gt;&lt;\/item&gt;
<item  id="122" filename="fyp/MA_UNITDATAX_request.c" linenumber="67" name="icmp_ln67" contextFuncName="ma_unitdatax_request" moduleName="ma_unitdatax_request" rtlName="icmp_ln67_fu_561_p2" latency="0" BRAM="-1" DSP="-1" FF="0" LUT="9" fileDirectory="E:\FYP\HLS\MAC_SAP"&gt;&lt;\/item&gt;
<item  id="125" filename="fyp/MA_UNITDATAX_request.c" linenumber="80" name="add_ln80" contextFuncName="ma_unitdatax_request" moduleName="ma_unitdatax_request" rtlName="add_ln80_fu_567_p2" latency="0" BRAM="-1" DSP="-1" FF="0" LUT="13" fileDirectory="E:\FYP\HLS\MAC_SAP"&gt;&lt;\/item&gt;
<item  id="126" filename="fyp/MA_UNITDATAX_request.c" linenumber="80" name="tmp_6" contextFuncName="ma_unitdatax_request" moduleName="ma_unitdatax_request" rtlName="tmp_6_fu_572_p4" latency="0" BRAM="-1" DSP="-1" FF="-1" LUT="-1" fileDirectory="E:\FYP\HLS\MAC_SAP"&gt;&lt;\/item&gt;
<item  id="127" filename="fyp/MA_UNITDATAX_request.c" linenumber="80" name="icmp_ln80" contextFuncName="ma_unitdatax_request" moduleName="ma_unitdatax_request" rtlName="icmp_ln80_fu_582_p2" latency="0" BRAM="-1" DSP="-1" FF="0" LUT="9" fileDirectory="E:\FYP\HLS\MAC_SAP"&gt;&lt;\/item&gt;
<item  id="130" filename="fyp/MA_UNITDATAX_request.c" linenumber="81" name="enqueue_res_vo" contextFuncName="ma_unitdatax_request" moduleName="ma_unitdatax_request" rtlName="grp_enqueue_dequeue_fram_fu_257" latency="1" BRAM="-1" DSP="-1" FF="-1" LUT="-1" fileDirectory="E:\FYP\HLS\MAC_SAP"&gt;&lt;\/item&gt;
<item  id="131" filename="fyp/MA_UNITDATAX_request.c" linenumber="82" name="icmp_ln82" contextFuncName="ma_unitdatax_request" moduleName="ma_unitdatax_request" rtlName="grp_fu_336_p2" latency="0" BRAM="-1" DSP="-1" FF="0" LUT="9" fileDirectory="E:\FYP\HLS\MAC_SAP"&gt;&lt;\/item&gt;
<item  id="134" filename="fyp/MA_UNITDATAX_request.c" linenumber="90" name="_ln90" contextFuncName="ma_unitdatax_request" moduleName="ma_unitdatax_request" rtlName="grp_ma_unitdatax_status_s_fu_313" latency="0" BRAM="-1" DSP="-1" FF="-1" LUT="-1" fileDirectory="E:\FYP\HLS\MAC_SAP"&gt;&lt;\/item&gt;
<item  id="140" filename="fyp/edca.c" linenumber="328" name="tmp_i3" contextFuncName="start_backoff_vo" moduleName="ma_unitdatax_request" rtlName="grp_random_int_gen_fu_295" latency="1" BRAM="-1" DSP="-1" FF="-1" LUT="-1" fileDirectory="E:\FYP\HLS\MAC_SAP"&gt;&lt;\/item&gt;
<item  id="144" filename="fyp/MA_UNITDATAX_request.c" linenumber="86" name="_ln86" contextFuncName="ma_unitdatax_request" moduleName="ma_unitdatax_request" rtlName="grp_ma_unitdatax_status_s_fu_313" latency="0" BRAM="-1" DSP="-1" FF="-1" LUT="-1" fileDirectory="E:\FYP\HLS\MAC_SAP"&gt;&lt;\/item&gt;
<item  id="145" filename="fyp/MA_UNITDATAX_request.c" linenumber="87" name="add_ln87" contextFuncName="ma_unitdatax_request" moduleName="ma_unitdatax_request" rtlName="grp_fu_342_p2" latency="0" BRAM="-1" DSP="-1" FF="0" LUT="19" fileDirectory="E:\FYP\HLS\MAC_SAP"&gt;&lt;\/item&gt;
<item  id="149" filename="fyp/MA_UNITDATAX_request.c" linenumber="68" name="enqueue_res_vi" contextFuncName="ma_unitdatax_request" moduleName="ma_unitdatax_request" rtlName="grp_enqueue_dequeue_fram_fu_257" latency="1" BRAM="-1" DSP="-1" FF="-1" LUT="-1" fileDirectory="E:\FYP\HLS\MAC_SAP"&gt;&lt;\/item&gt;
<item  id="150" filename="fyp/MA_UNITDATAX_request.c" linenumber="69" name="icmp_ln69" contextFuncName="ma_unitdatax_request" moduleName="ma_unitdatax_request" rtlName="grp_fu_336_p2" latency="0" BRAM="-1" DSP="-1" FF="0" LUT="9" fileDirectory="E:\FYP\HLS\MAC_SAP"&gt;&lt;\/item&gt;
<item  id="153" filename="fyp/MA_UNITDATAX_request.c" linenumber="77" name="_ln77" contextFuncName="ma_unitdatax_request" moduleName="ma_unitdatax_request" rtlName="grp_ma_unitdatax_status_s_fu_313" latency="0" BRAM="-1" DSP="-1" FF="-1" LUT="-1" fileDirectory="E:\FYP\HLS\MAC_SAP"&gt;&lt;\/item&gt;
<item  id="160" filename="fyp/edca.c" linenumber="339" name="tmp_i2" contextFuncName="start_backoff_vi" moduleName="ma_unitdatax_request" rtlName="grp_random_int_gen_fu_295" latency="1" BRAM="-1" DSP="-1" FF="-1" LUT="-1" fileDirectory="E:\FYP\HLS\MAC_SAP"&gt;&lt;\/item&gt;
<item  id="164" filename="fyp/MA_UNITDATAX_request.c" linenumber="73" name="_ln73" contextFuncName="ma_unitdatax_request" moduleName="ma_unitdatax_request" rtlName="grp_ma_unitdatax_status_s_fu_313" latency="0" BRAM="-1" DSP="-1" FF="-1" LUT="-1" fileDirectory="E:\FYP\HLS\MAC_SAP"&gt;&lt;\/item&gt;
<item  id="165" filename="fyp/MA_UNITDATAX_request.c" linenumber="74" name="add_ln74" contextFuncName="ma_unitdatax_request" moduleName="ma_unitdatax_request" rtlName="grp_fu_342_p2" latency="0" BRAM="-1" DSP="-1" FF="0" LUT="19" fileDirectory="E:\FYP\HLS\MAC_SAP"&gt;&lt;\/item&gt;
<item  id="169" filename="fyp/MA_UNITDATAX_request.c" linenumber="55" name="enqueue_res_be" contextFuncName="ma_unitdatax_request" moduleName="ma_unitdatax_request" rtlName="grp_enqueue_dequeue_fram_fu_257" latency="1" BRAM="-1" DSP="-1" FF="-1" LUT="-1" fileDirectory="E:\FYP\HLS\MAC_SAP"&gt;&lt;\/item&gt;
<item  id="170" filename="fyp/MA_UNITDATAX_request.c" linenumber="56" name="icmp_ln56" contextFuncName="ma_unitdatax_request" moduleName="ma_unitdatax_request" rtlName="grp_fu_336_p2" latency="0" BRAM="-1" DSP="-1" FF="0" LUT="9" fileDirectory="E:\FYP\HLS\MAC_SAP"&gt;&lt;\/item&gt;
<item  id="173" filename="fyp/MA_UNITDATAX_request.c" linenumber="64" name="_ln64" contextFuncName="ma_unitdatax_request" moduleName="ma_unitdatax_request" rtlName="grp_ma_unitdatax_status_s_fu_313" latency="0" BRAM="-1" DSP="-1" FF="-1" LUT="-1" fileDirectory="E:\FYP\HLS\MAC_SAP"&gt;&lt;\/item&gt;
<item  id="180" filename="fyp/edca.c" linenumber="350" name="tmp_i1" contextFuncName="start_backoff_be" moduleName="ma_unitdatax_request" rtlName="grp_random_int_gen_fu_295" latency="1" BRAM="-1" DSP="-1" FF="-1" LUT="-1" fileDirectory="E:\FYP\HLS\MAC_SAP"&gt;&lt;\/item&gt;
<item  id="184" filename="fyp/MA_UNITDATAX_request.c" linenumber="60" name="_ln60" contextFuncName="ma_unitdatax_request" moduleName="ma_unitdatax_request" rtlName="grp_ma_unitdatax_status_s_fu_313" latency="0" BRAM="-1" DSP="-1" FF="-1" LUT="-1" fileDirectory="E:\FYP\HLS\MAC_SAP"&gt;&lt;\/item&gt;
<item  id="185" filename="fyp/MA_UNITDATAX_request.c" linenumber="61" name="add_ln61" contextFuncName="ma_unitdatax_request" moduleName="ma_unitdatax_request" rtlName="grp_fu_342_p2" latency="0" BRAM="-1" DSP="-1" FF="0" LUT="19" fileDirectory="E:\FYP\HLS\MAC_SAP"&gt;&lt;\/item&gt;
<item  id="189" filename="fyp/MA_UNITDATAX_request.c" linenumber="42" name="enqueue_res_bk" contextFuncName="ma_unitdatax_request" moduleName="ma_unitdatax_request" rtlName="grp_enqueue_dequeue_fram_fu_257" latency="1" BRAM="-1" DSP="-1" FF="-1" LUT="-1" fileDirectory="E:\FYP\HLS\MAC_SAP"&gt;&lt;\/item&gt;
<item  id="190" filename="fyp/MA_UNITDATAX_request.c" linenumber="43" name="icmp_ln43" contextFuncName="ma_unitdatax_request" moduleName="ma_unitdatax_request" rtlName="grp_fu_336_p2" latency="0" BRAM="-1" DSP="-1" FF="0" LUT="9" fileDirectory="E:\FYP\HLS\MAC_SAP"&gt;&lt;\/item&gt;
<item  id="193" filename="fyp/MA_UNITDATAX_request.c" linenumber="51" name="_ln51" contextFuncName="ma_unitdatax_request" moduleName="ma_unitdatax_request" rtlName="grp_ma_unitdatax_status_s_fu_313" latency="0" BRAM="-1" DSP="-1" FF="-1" LUT="-1" fileDirectory="E:\FYP\HLS\MAC_SAP"&gt;&lt;\/item&gt;
<item  id="200" filename="fyp/edca.c" linenumber="361" name="tmp_i" contextFuncName="start_backoff_bk" moduleName="ma_unitdatax_request" rtlName="grp_random_int_gen_fu_295" latency="1" BRAM="-1" DSP="-1" FF="-1" LUT="-1" fileDirectory="E:\FYP\HLS\MAC_SAP"&gt;&lt;\/item&gt;
<item  id="204" filename="fyp/MA_UNITDATAX_request.c" linenumber="47" name="_ln47" contextFuncName="ma_unitdatax_request" moduleName="ma_unitdatax_request" rtlName="grp_ma_unitdatax_status_s_fu_313" latency="0" BRAM="-1" DSP="-1" FF="-1" LUT="-1" fileDirectory="E:\FYP\HLS\MAC_SAP"&gt;&lt;\/item&gt;
<item  id="205" filename="fyp/MA_UNITDATAX_request.c" linenumber="48" name="add_ln48" contextFuncName="ma_unitdatax_request" moduleName="ma_unitdatax_request" rtlName="grp_fu_342_p2" latency="0" BRAM="-1" DSP="-1" FF="0" LUT="19" fileDirectory="E:\FYP\HLS\MAC_SAP"&gt;&lt;\/item&gt;
<item  id="209" filename="fyp/MA_UNITDATAX_request.c" linenumber="28" name="_ln28" contextFuncName="ma_unitdatax_request" moduleName="ma_unitdatax_request" rtlName="grp_ma_unitdatax_status_s_fu_313" latency="0" BRAM="-1" DSP="-1" FF="-1" LUT="-1" fileDirectory="E:\FYP\HLS\MAC_SAP"&gt;&lt;\/item&gt;
<item  id="212" filename="fyp/MA_UNITDATAX_request.c" linenumber="16" name="_ln16" contextFuncName="ma_unitdatax_request" moduleName="ma_unitdatax_request" rtlName="grp_ma_unitdatax_status_s_fu_313" latency="0" BRAM="-1" DSP="-1" FF="-1" LUT="-1" fileDirectory="E:\FYP\HLS\MAC_SAP"&gt;&lt;\/item&gt;
&lt;\/annotationInfo&gt;
<annotationInfo>
<item  id="12" filename="fyp/timer.c" linenumber="8" name="zext_ln8" contextFuncName="start_timer" moduleName="start_timer" rtlName="zext_ln8_fu_99_p1" latency="0" BRAM="-1" DSP="-1" FF="-1" LUT="-1" fileDirectory="E:\FYP\HLS\MAC_SAP"&gt;&lt;\/item&gt;
<item  id="14" filename="fyp/timer.c" linenumber="8" name="sext_ln8_1" contextFuncName="start_timer" moduleName="start_timer" rtlName="sext_ln8_1_fu_106_p1" latency="0" BRAM="-1" DSP="-1" FF="-1" LUT="-1" fileDirectory="E:\FYP\HLS\MAC_SAP"&gt;&lt;\/item&gt;
<item  id="15" filename="fyp/timer.c" linenumber="8" name="zext_ln8_1" contextFuncName="start_timer" moduleName="start_timer" rtlName="zext_ln8_1_fu_110_p1" latency="0" BRAM="-1" DSP="-1" FF="-1" LUT="-1" fileDirectory="E:\FYP\HLS\MAC_SAP"&gt;&lt;\/item&gt;
<item  id="16" filename="fyp/timer.c" linenumber="8" name="add_ln8" contextFuncName="start_timer" moduleName="start_timer" rtlName="add_ln8_fu_114_p2" latency="0" BRAM="-1" DSP="-1" FF="0" LUT="16" fileDirectory="E:\FYP\HLS\MAC_SAP"&gt;&lt;\/item&gt;
<item  id="17" filename="fyp/timer.c" linenumber="8" name="sext_ln8" contextFuncName="start_timer" moduleName="start_timer" rtlName="sext_ln8_fu_120_p1" latency="0" BRAM="-1" DSP="-1" FF="-1" LUT="-1" fileDirectory="E:\FYP\HLS\MAC_SAP"&gt;&lt;\/item&gt;
<item  id="18" filename="fyp/timer.c" linenumber="8" name="icmp_ln8" contextFuncName="start_timer" moduleName="start_timer" rtlName="icmp_ln8_fu_124_p2" latency="0" BRAM="-1" DSP="-1" FF="0" LUT="18" fileDirectory="E:\FYP\HLS\MAC_SAP"&gt;&lt;\/item&gt;
<item  id="19" filename="fyp/timer.c" linenumber="8" name="i" contextFuncName="start_timer" moduleName="start_timer" rtlName="i_fu_130_p2" latency="0" BRAM="-1" DSP="-1" FF="0" LUT="27" fileDirectory="E:\FYP\HLS\MAC_SAP"&gt;&lt;\/item&gt;
<item  id="25" filename="fyp/timer.c" linenumber="17" name="tc_1" contextFuncName="start_timer" moduleName="start_timer" rtlName="grp_fu_73_p2" latency="0" BRAM="-1" DSP="-1" FF="0" LUT="23" fileDirectory="E:\FYP\HLS\MAC_SAP"&gt;&lt;\/item&gt;
<item  id="33" filename="fyp/timer.c" linenumber="11" name="tc_2" contextFuncName="start_timer" moduleName="start_timer" rtlName="grp_fu_73_p2" latency="0" BRAM="-1" DSP="-1" FF="0" LUT="23" fileDirectory="E:\FYP\HLS\MAC_SAP"&gt;&lt;\/item&gt;
&lt;\/annotationInfo&gt;
<annotationInfo>
<item  id="4" filename="fyp/edca.c" linenumber="187" name="icmp_ln187" contextFuncName="slot_boundary_timing" moduleName="slot_boundary_timing" rtlName="icmp_ln187_fu_64_p2" latency="0" BRAM="-1" DSP="-1" FF="0" LUT="9" fileDirectory="E:\FYP\HLS\MAC_SAP"&gt;&lt;\/item&gt;
<item  id="7" filename="fyp/edca.c" linenumber="203" name="icmp_ln203" contextFuncName="slot_boundary_timing" moduleName="slot_boundary_timing" rtlName="icmp_ln203_fu_70_p2" latency="0" BRAM="-1" DSP="-1" FF="0" LUT="9" fileDirectory="E:\FYP\HLS\MAC_SAP"&gt;&lt;\/item&gt;
<item  id="10" filename="fyp/edca.c" linenumber="213" name="icmp_ln213" contextFuncName="slot_boundary_timing" moduleName="slot_boundary_timing" rtlName="icmp_ln213_fu_76_p2" latency="0" BRAM="-1" DSP="-1" FF="0" LUT="9" fileDirectory="E:\FYP\HLS\MAC_SAP"&gt;&lt;\/item&gt;
<item  id="13" filename="fyp/edca.c" linenumber="229" name="icmp_ln229" contextFuncName="slot_boundary_timing" moduleName="slot_boundary_timing" rtlName="icmp_ln229_fu_82_p2" latency="0" BRAM="-1" DSP="-1" FF="0" LUT="9" fileDirectory="E:\FYP\HLS\MAC_SAP"&gt;&lt;\/item&gt;
<item  id="16" filename="fyp/edca.c" linenumber="239" name="icmp_ln239" contextFuncName="slot_boundary_timing" moduleName="slot_boundary_timing" rtlName="icmp_ln239_fu_88_p2" latency="0" BRAM="-1" DSP="-1" FF="0" LUT="9" fileDirectory="E:\FYP\HLS\MAC_SAP"&gt;&lt;\/item&gt;
<item  id="19" filename="fyp/edca.c" linenumber="241" name="idle_timeout_4" contextFuncName="slot_boundary_timing" moduleName="slot_boundary_timing" rtlName="grp_start_timer_fu_53" latency="1" BRAM="-1" DSP="-1" FF="-1" LUT="-1" fileDirectory="E:\FYP\HLS\MAC_SAP"&gt;&lt;\/item&gt;
<item  id="22" filename="fyp/edca.c" linenumber="231" name="idle_timeout_3" contextFuncName="slot_boundary_timing" moduleName="slot_boundary_timing" rtlName="grp_start_timer_fu_53" latency="1" BRAM="-1" DSP="-1" FF="-1" LUT="-1" fileDirectory="E:\FYP\HLS\MAC_SAP"&gt;&lt;\/item&gt;
<item  id="25" filename="fyp/edca.c" linenumber="216" name="sifs_timeout_1" contextFuncName="slot_boundary_timing" moduleName="slot_boundary_timing" rtlName="grp_start_timer_fu_53" latency="1" BRAM="-1" DSP="-1" FF="-1" LUT="-1" fileDirectory="E:\FYP\HLS\MAC_SAP"&gt;&lt;\/item&gt;
<item  id="28" filename="fyp/edca.c" linenumber="218" name="idle_timeout_2" contextFuncName="slot_boundary_timing" moduleName="slot_boundary_timing" rtlName="grp_start_timer_fu_53" latency="1" BRAM="-1" DSP="-1" FF="-1" LUT="-1" fileDirectory="E:\FYP\HLS\MAC_SAP"&gt;&lt;\/item&gt;
<item  id="31" filename="fyp/edca.c" linenumber="205" name="idle_timeout_1" contextFuncName="slot_boundary_timing" moduleName="slot_boundary_timing" rtlName="grp_start_timer_fu_53" latency="1" BRAM="-1" DSP="-1" FF="-1" LUT="-1" fileDirectory="E:\FYP\HLS\MAC_SAP"&gt;&lt;\/item&gt;
<item  id="34" filename="fyp/edca.c" linenumber="190" name="sifs_timeout" contextFuncName="slot_boundary_timing" moduleName="slot_boundary_timing" rtlName="grp_start_timer_fu_53" latency="1" BRAM="-1" DSP="-1" FF="-1" LUT="-1" fileDirectory="E:\FYP\HLS\MAC_SAP"&gt;&lt;\/item&gt;
<item  id="37" filename="fyp/edca.c" linenumber="192" name="idle_timeout" contextFuncName="slot_boundary_timing" moduleName="slot_boundary_timing" rtlName="grp_start_timer_fu_53" latency="1" BRAM="-1" DSP="-1" FF="-1" LUT="-1" fileDirectory="E:\FYP\HLS\MAC_SAP"&gt;&lt;\/item&gt;
&lt;\/annotationInfo&gt;
<annotationInfo>
<item  id="9" filename="fyp/edca.c" linenumber="254" name="tmp" contextFuncName="backoff_vo" moduleName="backoff_vo" rtlName="tmp_reg_80" latency="0" BRAM="-1" DSP="-1" FF="-1" LUT="-1" fileDirectory="E:\FYP\HLS\MAC_SAP"&gt;&lt;\/item&gt;
<item  id="13" filename="fyp/edca.c" linenumber="255" name="icmp_ln255" contextFuncName="backoff_vo" moduleName="backoff_vo" rtlName="icmp_ln255_fu_56_p2" latency="0" BRAM="-1" DSP="-1" FF="0" LUT="13" fileDirectory="E:\FYP\HLS\MAC_SAP"&gt;&lt;\/item&gt;
<item  id="16" filename="fyp/edca.c" linenumber="260" name="add_ln260" contextFuncName="backoff_vo" moduleName="backoff_vo" rtlName="add_ln260_fu_62_p2" latency="0" BRAM="-1" DSP="-1" FF="0" LUT="17" fileDirectory="E:\FYP\HLS\MAC_SAP"&gt;&lt;\/item&gt;
<item  id="21" filename="fyp/edca.c" linenumber="328" name="tmp_i" contextFuncName="start_backoff_vo" moduleName="backoff_vo" rtlName="grp_random_int_gen_fu_32" latency="1" BRAM="-1" DSP="-1" FF="-1" LUT="-1" fileDirectory="E:\FYP\HLS\MAC_SAP"&gt;&lt;\/item&gt;
&lt;\/annotationInfo&gt;
<annotationInfo>
<item  id="15" filename="fyp/edca.c" linenumber="335" name="icmp_ln335" contextFuncName="start_backoff_vi" moduleName="start_backoff_vi" rtlName="icmp_ln335_fu_56_p2" latency="0" BRAM="-1" DSP="-1" FF="0" LUT="13" fileDirectory="E:\FYP\HLS\MAC_SAP"&gt;&lt;\/item&gt;
<item  id="18" filename="fyp/edca.c" linenumber="336" name="shl_ln336" contextFuncName="start_backoff_vi" moduleName="start_backoff_vi" rtlName="shl_ln336_fu_62_p2" latency="0" BRAM="-1" DSP="-1" FF="-1" LUT="-1" fileDirectory="E:\FYP\HLS\MAC_SAP"&gt;&lt;\/item&gt;
<item  id="19" filename="fyp/edca.c" linenumber="336" name="or_ln336" contextFuncName="start_backoff_vi" moduleName="start_backoff_vi" rtlName="or_ln336_fu_68_p2" latency="0" BRAM="-1" DSP="-1" FF="0" LUT="10" fileDirectory="E:\FYP\HLS\MAC_SAP"&gt;&lt;\/item&gt;
<item  id="24" filename="fyp/edca.c" linenumber="339" name="tmp" contextFuncName="start_backoff_vi" moduleName="start_backoff_vi" rtlName="grp_random_int_gen_fu_37" latency="1" BRAM="-1" DSP="-1" FF="-1" LUT="-1" fileDirectory="E:\FYP\HLS\MAC_SAP"&gt;&lt;\/item&gt;
&lt;\/annotationInfo&gt;
<annotationInfo>
<item  id="15" filename="fyp/edca.c" linenumber="346" name="icmp_ln346" contextFuncName="start_backoff_be" moduleName="start_backoff_be" rtlName="icmp_ln346_fu_56_p2" latency="0" BRAM="-1" DSP="-1" FF="0" LUT="13" fileDirectory="E:\FYP\HLS\MAC_SAP"&gt;&lt;\/item&gt;
<item  id="18" filename="fyp/edca.c" linenumber="347" name="shl_ln347" contextFuncName="start_backoff_be" moduleName="start_backoff_be" rtlName="shl_ln347_fu_62_p2" latency="0" BRAM="-1" DSP="-1" FF="-1" LUT="-1" fileDirectory="E:\FYP\HLS\MAC_SAP"&gt;&lt;\/item&gt;
<item  id="19" filename="fyp/edca.c" linenumber="347" name="or_ln347" contextFuncName="start_backoff_be" moduleName="start_backoff_be" rtlName="or_ln347_fu_68_p2" latency="0" BRAM="-1" DSP="-1" FF="0" LUT="10" fileDirectory="E:\FYP\HLS\MAC_SAP"&gt;&lt;\/item&gt;
<item  id="24" filename="fyp/edca.c" linenumber="350" name="tmp" contextFuncName="start_backoff_be" moduleName="start_backoff_be" rtlName="grp_random_int_gen_fu_37" latency="1" BRAM="-1" DSP="-1" FF="-1" LUT="-1" fileDirectory="E:\FYP\HLS\MAC_SAP"&gt;&lt;\/item&gt;
&lt;\/annotationInfo&gt;
<annotationInfo>
<item  id="15" filename="fyp/edca.c" linenumber="357" name="icmp_ln357" contextFuncName="start_backoff_bk" moduleName="start_backoff_bk" rtlName="icmp_ln357_fu_56_p2" latency="0" BRAM="-1" DSP="-1" FF="0" LUT="13" fileDirectory="E:\FYP\HLS\MAC_SAP"&gt;&lt;\/item&gt;
<item  id="18" filename="fyp/edca.c" linenumber="358" name="shl_ln358" contextFuncName="start_backoff_bk" moduleName="start_backoff_bk" rtlName="shl_ln358_fu_62_p2" latency="0" BRAM="-1" DSP="-1" FF="-1" LUT="-1" fileDirectory="E:\FYP\HLS\MAC_SAP"&gt;&lt;\/item&gt;
<item  id="19" filename="fyp/edca.c" linenumber="358" name="or_ln358" contextFuncName="start_backoff_bk" moduleName="start_backoff_bk" rtlName="or_ln358_fu_68_p2" latency="0" BRAM="-1" DSP="-1" FF="0" LUT="10" fileDirectory="E:\FYP\HLS\MAC_SAP"&gt;&lt;\/item&gt;
<item  id="24" filename="fyp/edca.c" linenumber="361" name="tmp" contextFuncName="start_backoff_bk" moduleName="start_backoff_bk" rtlName="grp_random_int_gen_fu_37" latency="1" BRAM="-1" DSP="-1" FF="-1" LUT="-1" fileDirectory="E:\FYP\HLS\MAC_SAP"&gt;&lt;\/item&gt;
&lt;\/annotationInfo&gt;
<annotationInfo>
<item  id="20" filename="fyp/edca.c" linenumber="368" name="trunc_ln368" contextFuncName="start_tx" moduleName="start_tx" rtlName="trunc_ln368_fu_79_p1" latency="0" BRAM="-1" DSP="-1" FF="-1" LUT="-1" fileDirectory="E:\FYP\HLS\MAC_SAP"&gt;&lt;\/item&gt;
<item  id="21" filename="fyp/edca.c" linenumber="368" name="add_ln368" contextFuncName="start_tx" moduleName="start_tx" rtlName="add_ln368_fu_83_p2" latency="0" BRAM="-1" DSP="-1" FF="0" LUT="10" fileDirectory="E:\FYP\HLS\MAC_SAP"&gt;&lt;\/item&gt;
<item  id="22" filename="fyp/edca.c" linenumber="368" name="empty" contextFuncName="start_tx" moduleName="start_tx" rtlName="grp_enqueue_dequeue_fram_fu_44" latency="1" BRAM="-1" DSP="-1" FF="-1" LUT="-1" fileDirectory="E:\FYP\HLS\MAC_SAP"&gt;&lt;\/item&gt;
&lt;\/annotationInfo&gt;
<annotationInfo>
<item  id="31" filename="fyp/initial_edca_proc.c" linenumber="6" name="idle_waited" contextFuncName="initial_edca_process" moduleName="initial_edca_process" rtlName="grp_slot_boundary_timing_fu_204" latency="1" BRAM="-1" DSP="-1" FF="-1" LUT="-1" fileDirectory="E:\FYP\HLS\MAC_SAP"&gt;&lt;\/item&gt;
<item  id="37" filename="fyp/initial_edca_proc.c" linenumber="8" name="_ln8" contextFuncName="initial_edca_process" moduleName="initial_edca_process" rtlName="grp_backoff_vo_fu_153" latency="1" BRAM="-1" DSP="-1" FF="-1" LUT="-1" fileDirectory="E:\FYP\HLS\MAC_SAP"&gt;&lt;\/item&gt;
<item  id="40" filename="fyp/edca.c" linenumber="267" name="tmp" contextFuncName="backoff_vi" moduleName="initial_edca_process" rtlName="tmp_reg_348" latency="0" BRAM="-1" DSP="-1" FF="-1" LUT="-1" fileDirectory="E:\FYP\HLS\MAC_SAP"&gt;&lt;\/item&gt;
<item  id="44" filename="fyp/edca.c" linenumber="268" name="icmp_ln268" contextFuncName="backoff_vi" moduleName="initial_edca_process" rtlName="icmp_ln268_fu_235_p2" latency="0" BRAM="-1" DSP="-1" FF="0" LUT="13" fileDirectory="E:\FYP\HLS\MAC_SAP"&gt;&lt;\/item&gt;
<item  id="47" filename="fyp/edca.c" linenumber="278" name="add_ln278" contextFuncName="backoff_vi" moduleName="initial_edca_process" rtlName="add_ln278_fu_241_p2" latency="0" BRAM="-1" DSP="-1" FF="0" LUT="17" fileDirectory="E:\FYP\HLS\MAC_SAP"&gt;&lt;\/item&gt;
<item  id="51" filename="fyp/edca.c" linenumber="269" name="icmp_ln269" contextFuncName="backoff_vi" moduleName="initial_edca_process" rtlName="icmp_ln269_fu_253_p2" latency="0" BRAM="-1" DSP="-1" FF="0" LUT="9" fileDirectory="E:\FYP\HLS\MAC_SAP"&gt;&lt;\/item&gt;
<item  id="54" filename="fyp/edca.c" linenumber="274" name="_ln274" contextFuncName="backoff_vi" moduleName="initial_edca_process" rtlName="grp_start_backoff_vi_fu_165" latency="1" BRAM="-1" DSP="-1" FF="-1" LUT="-1" fileDirectory="E:\FYP\HLS\MAC_SAP"&gt;&lt;\/item&gt;
<item  id="58" filename="fyp/edca.c" linenumber="271" name="_ln271" contextFuncName="backoff_vi" moduleName="initial_edca_process" rtlName="grp_start_backoff_vi_fu_165" latency="1" BRAM="-1" DSP="-1" FF="-1" LUT="-1" fileDirectory="E:\FYP\HLS\MAC_SAP"&gt;&lt;\/item&gt;
<item  id="63" filename="fyp/edca.c" linenumber="285" name="tmp_7" contextFuncName="backoff_be" moduleName="initial_edca_process" rtlName="tmp_7_reg_360" latency="0" BRAM="-1" DSP="-1" FF="-1" LUT="-1" fileDirectory="E:\FYP\HLS\MAC_SAP"&gt;&lt;\/item&gt;
<item  id="67" filename="fyp/edca.c" linenumber="286" name="icmp_ln286" contextFuncName="backoff_be" moduleName="initial_edca_process" rtlName="icmp_ln286_fu_275_p2" latency="0" BRAM="-1" DSP="-1" FF="0" LUT="13" fileDirectory="E:\FYP\HLS\MAC_SAP"&gt;&lt;\/item&gt;
<item  id="70" filename="fyp/edca.c" linenumber="296" name="add_ln296" contextFuncName="backoff_be" moduleName="initial_edca_process" rtlName="add_ln296_fu_281_p2" latency="0" BRAM="-1" DSP="-1" FF="0" LUT="17" fileDirectory="E:\FYP\HLS\MAC_SAP"&gt;&lt;\/item&gt;
<item  id="74" filename="fyp/edca.c" linenumber="287" name="tmp_8" contextFuncName="backoff_be" moduleName="initial_edca_process" rtlName="tmp_8_fu_293_p4" latency="0" BRAM="-1" DSP="-1" FF="-1" LUT="-1" fileDirectory="E:\FYP\HLS\MAC_SAP"&gt;&lt;\/item&gt;
<item  id="75" filename="fyp/edca.c" linenumber="287" name="icmp_ln287" contextFuncName="backoff_be" moduleName="initial_edca_process" rtlName="icmp_ln287_fu_303_p2" latency="0" BRAM="-1" DSP="-1" FF="0" LUT="8" fileDirectory="E:\FYP\HLS\MAC_SAP"&gt;&lt;\/item&gt;
<item  id="78" filename="fyp/edca.c" linenumber="292" name="_ln292" contextFuncName="backoff_be" moduleName="initial_edca_process" rtlName="grp_start_backoff_be_fu_178" latency="1" BRAM="-1" DSP="-1" FF="-1" LUT="-1" fileDirectory="E:\FYP\HLS\MAC_SAP"&gt;&lt;\/item&gt;
<item  id="82" filename="fyp/edca.c" linenumber="289" name="_ln289" contextFuncName="backoff_be" moduleName="initial_edca_process" rtlName="grp_start_backoff_be_fu_178" latency="1" BRAM="-1" DSP="-1" FF="-1" LUT="-1" fileDirectory="E:\FYP\HLS\MAC_SAP"&gt;&lt;\/item&gt;
<item  id="87" filename="fyp/edca.c" linenumber="303" name="tmp_9" contextFuncName="backoff_bk" moduleName="initial_edca_process" rtlName="tmp_9_reg_372" latency="0" BRAM="-1" DSP="-1" FF="-1" LUT="-1" fileDirectory="E:\FYP\HLS\MAC_SAP"&gt;&lt;\/item&gt;
<item  id="91" filename="fyp/edca.c" linenumber="304" name="icmp_ln304" contextFuncName="backoff_bk" moduleName="initial_edca_process" rtlName="icmp_ln304_fu_325_p2" latency="0" BRAM="-1" DSP="-1" FF="0" LUT="13" fileDirectory="E:\FYP\HLS\MAC_SAP"&gt;&lt;\/item&gt;
<item  id="94" filename="fyp/edca.c" linenumber="314" name="add_ln314" contextFuncName="backoff_bk" moduleName="initial_edca_process" rtlName="add_ln314_fu_331_p2" latency="0" BRAM="-1" DSP="-1" FF="0" LUT="17" fileDirectory="E:\FYP\HLS\MAC_SAP"&gt;&lt;\/item&gt;
<item  id="98" filename="fyp/edca.c" linenumber="305" name="icmp_ln305" contextFuncName="backoff_bk" moduleName="initial_edca_process" rtlName="grp_fu_213_p2" latency="0" BRAM="-1" DSP="-1" FF="0" LUT="9" fileDirectory="E:\FYP\HLS\MAC_SAP"&gt;&lt;\/item&gt;
<item  id="101" filename="fyp/edca.c" linenumber="310" name="_ln310" contextFuncName="backoff_bk" moduleName="initial_edca_process" rtlName="grp_start_backoff_bk_fu_191" latency="1" BRAM="-1" DSP="-1" FF="-1" LUT="-1" fileDirectory="E:\FYP\HLS\MAC_SAP"&gt;&lt;\/item&gt;
<item  id="105" filename="fyp/edca.c" linenumber="307" name="_ln307" contextFuncName="backoff_bk" moduleName="initial_edca_process" rtlName="grp_start_backoff_bk_fu_191" latency="1" BRAM="-1" DSP="-1" FF="-1" LUT="-1" fileDirectory="E:\FYP\HLS\MAC_SAP"&gt;&lt;\/item&gt;
<item  id="109" filename="fyp/initial_edca_proc.c" linenumber="12" name="icmp_ln12" contextFuncName="initial_edca_process" moduleName="initial_edca_process" rtlName="grp_fu_213_p2" latency="0" BRAM="-1" DSP="-1" FF="0" LUT="9" fileDirectory="E:\FYP\HLS\MAC_SAP"&gt;&lt;\/item&gt;
<item  id="112" filename="fyp/initial_edca_proc.c" linenumber="17" name="idle_waited_2" contextFuncName="initial_edca_process" moduleName="initial_edca_process" rtlName="grp_slot_boundary_timing_fu_204" latency="1" BRAM="-1" DSP="-1" FF="-1" LUT="-1" fileDirectory="E:\FYP\HLS\MAC_SAP"&gt;&lt;\/item&gt;
<item  id="115" filename="fyp/initial_edca_proc.c" linenumber="13" name="_ln13" contextFuncName="initial_edca_process" moduleName="initial_edca_process" rtlName="grp_start_tx_fu_119" latency="1" BRAM="-1" DSP="-1" FF="-1" LUT="-1" fileDirectory="E:\FYP\HLS\MAC_SAP"&gt;&lt;\/item&gt;
&lt;\/annotationInfo&gt;
<annotationInfo>
&lt;\/annotationInfo&gt;
<annotationInfo>
&lt;\/annotationInfo&gt;
<annotationInfo>
&lt;\/annotationInfo&gt;
<annotationInfo>
<item  id="31" filename="fyp/PHY_TXEND_confirm.c" linenumber="7" name="idle_waited" contextFuncName="phy_txend_confirm" moduleName="phy_txend_confirm" rtlName="grp_slot_boundary_timing_fu_202" latency="1" BRAM="-1" DSP="-1" FF="-1" LUT="-1" fileDirectory="E:\FYP\HLS\MAC_SAP"&gt;&lt;\/item&gt;
<item  id="37" filename="fyp/PHY_TXEND_confirm.c" linenumber="9" name="_ln9" contextFuncName="phy_txend_confirm" moduleName="phy_txend_confirm" rtlName="grp_backoff_vo_fu_151" latency="1" BRAM="-1" DSP="-1" FF="-1" LUT="-1" fileDirectory="E:\FYP\HLS\MAC_SAP"&gt;&lt;\/item&gt;
<item  id="40" filename="fyp/edca.c" linenumber="267" name="tmp" contextFuncName="backoff_vi" moduleName="phy_txend_confirm" rtlName="tmp_reg_346" latency="0" BRAM="-1" DSP="-1" FF="-1" LUT="-1" fileDirectory="E:\FYP\HLS\MAC_SAP"&gt;&lt;\/item&gt;
<item  id="44" filename="fyp/edca.c" linenumber="268" name="icmp_ln268" contextFuncName="backoff_vi" moduleName="phy_txend_confirm" rtlName="icmp_ln268_fu_233_p2" latency="0" BRAM="-1" DSP="-1" FF="0" LUT="13" fileDirectory="E:\FYP\HLS\MAC_SAP"&gt;&lt;\/item&gt;
<item  id="47" filename="fyp/edca.c" linenumber="278" name="add_ln278" contextFuncName="backoff_vi" moduleName="phy_txend_confirm" rtlName="add_ln278_fu_239_p2" latency="0" BRAM="-1" DSP="-1" FF="0" LUT="17" fileDirectory="E:\FYP\HLS\MAC_SAP"&gt;&lt;\/item&gt;
<item  id="51" filename="fyp/edca.c" linenumber="269" name="icmp_ln269" contextFuncName="backoff_vi" moduleName="phy_txend_confirm" rtlName="icmp_ln269_fu_251_p2" latency="0" BRAM="-1" DSP="-1" FF="0" LUT="9" fileDirectory="E:\FYP\HLS\MAC_SAP"&gt;&lt;\/item&gt;
<item  id="54" filename="fyp/edca.c" linenumber="274" name="_ln274" contextFuncName="backoff_vi" moduleName="phy_txend_confirm" rtlName="grp_start_backoff_vi_fu_163" latency="1" BRAM="-1" DSP="-1" FF="-1" LUT="-1" fileDirectory="E:\FYP\HLS\MAC_SAP"&gt;&lt;\/item&gt;
<item  id="58" filename="fyp/edca.c" linenumber="271" name="_ln271" contextFuncName="backoff_vi" moduleName="phy_txend_confirm" rtlName="grp_start_backoff_vi_fu_163" latency="1" BRAM="-1" DSP="-1" FF="-1" LUT="-1" fileDirectory="E:\FYP\HLS\MAC_SAP"&gt;&lt;\/item&gt;
<item  id="63" filename="fyp/edca.c" linenumber="285" name="tmp_2" contextFuncName="backoff_be" moduleName="phy_txend_confirm" rtlName="tmp_2_reg_358" latency="0" BRAM="-1" DSP="-1" FF="-1" LUT="-1" fileDirectory="E:\FYP\HLS\MAC_SAP"&gt;&lt;\/item&gt;
<item  id="67" filename="fyp/edca.c" linenumber="286" name="icmp_ln286" contextFuncName="backoff_be" moduleName="phy_txend_confirm" rtlName="icmp_ln286_fu_273_p2" latency="0" BRAM="-1" DSP="-1" FF="0" LUT="13" fileDirectory="E:\FYP\HLS\MAC_SAP"&gt;&lt;\/item&gt;
<item  id="70" filename="fyp/edca.c" linenumber="296" name="add_ln296" contextFuncName="backoff_be" moduleName="phy_txend_confirm" rtlName="add_ln296_fu_279_p2" latency="0" BRAM="-1" DSP="-1" FF="0" LUT="17" fileDirectory="E:\FYP\HLS\MAC_SAP"&gt;&lt;\/item&gt;
<item  id="74" filename="fyp/edca.c" linenumber="287" name="tmp_3" contextFuncName="backoff_be" moduleName="phy_txend_confirm" rtlName="tmp_3_fu_291_p4" latency="0" BRAM="-1" DSP="-1" FF="-1" LUT="-1" fileDirectory="E:\FYP\HLS\MAC_SAP"&gt;&lt;\/item&gt;
<item  id="75" filename="fyp/edca.c" linenumber="287" name="icmp_ln287" contextFuncName="backoff_be" moduleName="phy_txend_confirm" rtlName="icmp_ln287_fu_301_p2" latency="0" BRAM="-1" DSP="-1" FF="0" LUT="8" fileDirectory="E:\FYP\HLS\MAC_SAP"&gt;&lt;\/item&gt;
<item  id="78" filename="fyp/edca.c" linenumber="292" name="_ln292" contextFuncName="backoff_be" moduleName="phy_txend_confirm" rtlName="grp_start_backoff_be_fu_176" latency="1" BRAM="-1" DSP="-1" FF="-1" LUT="-1" fileDirectory="E:\FYP\HLS\MAC_SAP"&gt;&lt;\/item&gt;
<item  id="82" filename="fyp/edca.c" linenumber="289" name="_ln289" contextFuncName="backoff_be" moduleName="phy_txend_confirm" rtlName="grp_start_backoff_be_fu_176" latency="1" BRAM="-1" DSP="-1" FF="-1" LUT="-1" fileDirectory="E:\FYP\HLS\MAC_SAP"&gt;&lt;\/item&gt;
<item  id="87" filename="fyp/edca.c" linenumber="303" name="tmp_4" contextFuncName="backoff_bk" moduleName="phy_txend_confirm" rtlName="tmp_4_reg_370" latency="0" BRAM="-1" DSP="-1" FF="-1" LUT="-1" fileDirectory="E:\FYP\HLS\MAC_SAP"&gt;&lt;\/item&gt;
<item  id="91" filename="fyp/edca.c" linenumber="304" name="icmp_ln304" contextFuncName="backoff_bk" moduleName="phy_txend_confirm" rtlName="icmp_ln304_fu_323_p2" latency="0" BRAM="-1" DSP="-1" FF="0" LUT="13" fileDirectory="E:\FYP\HLS\MAC_SAP"&gt;&lt;\/item&gt;
<item  id="94" filename="fyp/edca.c" linenumber="314" name="add_ln314" contextFuncName="backoff_bk" moduleName="phy_txend_confirm" rtlName="add_ln314_fu_329_p2" latency="0" BRAM="-1" DSP="-1" FF="0" LUT="17" fileDirectory="E:\FYP\HLS\MAC_SAP"&gt;&lt;\/item&gt;
<item  id="98" filename="fyp/edca.c" linenumber="305" name="icmp_ln305" contextFuncName="backoff_bk" moduleName="phy_txend_confirm" rtlName="grp_fu_211_p2" latency="0" BRAM="-1" DSP="-1" FF="0" LUT="9" fileDirectory="E:\FYP\HLS\MAC_SAP"&gt;&lt;\/item&gt;
<item  id="101" filename="fyp/edca.c" linenumber="310" name="_ln310" contextFuncName="backoff_bk" moduleName="phy_txend_confirm" rtlName="grp_start_backoff_bk_fu_189" latency="1" BRAM="-1" DSP="-1" FF="-1" LUT="-1" fileDirectory="E:\FYP\HLS\MAC_SAP"&gt;&lt;\/item&gt;
<item  id="105" filename="fyp/edca.c" linenumber="307" name="_ln307" contextFuncName="backoff_bk" moduleName="phy_txend_confirm" rtlName="grp_start_backoff_bk_fu_189" latency="1" BRAM="-1" DSP="-1" FF="-1" LUT="-1" fileDirectory="E:\FYP\HLS\MAC_SAP"&gt;&lt;\/item&gt;
<item  id="109" filename="fyp/PHY_TXEND_confirm.c" linenumber="13" name="icmp_ln13" contextFuncName="phy_txend_confirm" moduleName="phy_txend_confirm" rtlName="grp_fu_211_p2" latency="0" BRAM="-1" DSP="-1" FF="0" LUT="9" fileDirectory="E:\FYP\HLS\MAC_SAP"&gt;&lt;\/item&gt;
<item  id="112" filename="fyp/PHY_TXEND_confirm.c" linenumber="18" name="idle_waited_1" contextFuncName="phy_txend_confirm" moduleName="phy_txend_confirm" rtlName="grp_slot_boundary_timing_fu_202" latency="1" BRAM="-1" DSP="-1" FF="-1" LUT="-1" fileDirectory="E:\FYP\HLS\MAC_SAP"&gt;&lt;\/item&gt;
<item  id="115" filename="fyp/PHY_TXEND_confirm.c" linenumber="14" name="_ln14" contextFuncName="phy_txend_confirm" moduleName="phy_txend_confirm" rtlName="grp_start_tx_fu_117" latency="1" BRAM="-1" DSP="-1" FF="-1" LUT="-1" fileDirectory="E:\FYP\HLS\MAC_SAP"&gt;&lt;\/item&gt;
&lt;\/annotationInfo&gt;
<annotationInfo>
<item  id="82" filename="fyp/mac_layer.c" linenumber="11" name="_ln11" contextFuncName="send_frame" moduleName="send_frame" rtlName="grp_ma_unitdatax_request_fu_344" latency="1" BRAM="-1" DSP="-1" FF="-1" LUT="-1" fileDirectory="E:\FYP\HLS\MAC_SAP"><\/item>
<item  id="83" filename="fyp/mac_layer.c" linenumber="13" name="_ln13" contextFuncName="send_frame" moduleName="send_frame" rtlName="grp_ma_unitdatax_request_fu_344" latency="1" BRAM="-1" DSP="-1" FF="-1" LUT="-1" fileDirectory="E:\FYP\HLS\MAC_SAP"><\/item>
<item  id="84" filename="fyp/mac_layer.c" linenumber="19" name="_ln19" contextFuncName="send_frame" moduleName="send_frame" rtlName="grp_initial_edca_process_fu_240" latency="1" BRAM="-1" DSP="-1" FF="-1" LUT="-1" fileDirectory="E:\FYP\HLS\MAC_SAP"><\/item>
<item  id="87" filename="fyp/PHY_TXSTART_confirm.c" linenumber="6" name="_ln6" contextFuncName="phy_txstart_confirm" moduleName="send_frame" rtlName="call_ln6_phy_data_request_1_fu_435" latency="0" BRAM="-1" DSP="-1" FF="-1" LUT="-1" fileDirectory="E:\FYP\HLS\MAC_SAP"><\/item>
<item  id="91" filename="fyp/mac_layer.c" linenumber="22" name="icmp_ln22" contextFuncName="send_frame" moduleName="send_frame" rtlName="icmp_ln22_fu_445_p2" latency="0" BRAM="-1" DSP="-1" FF="0" LUT="11" fileDirectory="E:\FYP\HLS\MAC_SAP"><\/item>
<item  id="93" filename="fyp/mac_layer.c" linenumber="22" name="i" contextFuncName="send_frame" moduleName="send_frame" rtlName="i_fu_451_p2" latency="0" BRAM="-1" DSP="-1" FF="0" LUT="15" fileDirectory="E:\FYP\HLS\MAC_SAP"><\/item>
<item  id="97" filename="fyp/PHY_DATA_confirm.c" linenumber="10" name="icmp_ln10" contextFuncName="phy_data_confirm" moduleName="send_frame" rtlName="icmp_ln10_fu_461_p2" latency="0" BRAM="-1" DSP="-1" FF="0" LUT="11" fileDirectory="E:\FYP\HLS\MAC_SAP"><\/item>
<item  id="103" filename="fyp/PHY_DATA_confirm.c" linenumber="11" name="icmp_ln11" contextFuncName="phy_data_confirm" moduleName="send_frame" rtlName="icmp_ln11_fu_467_p2" latency="0" BRAM="-1" DSP="-1" FF="0" LUT="11" fileDirectory="E:\FYP\HLS\MAC_SAP"><\/item>
<item  id="105" filename="fyp/PHY_DATA_confirm.c" linenumber="11" name="q" contextFuncName="phy_data_confirm" moduleName="send_frame" rtlName="q_fu_473_p2" latency="0" BRAM="-1" DSP="-1" FF="0" LUT="15" fileDirectory="E:\FYP\HLS\MAC_SAP"><\/item>
<item  id="108" filename="fyp/PHY_DATA_confirm.c" linenumber="12" name="zext_ln12" contextFuncName="phy_data_confirm" moduleName="send_frame" rtlName="zext_ln12_fu_479_p1" latency="0" BRAM="-1" DSP="-1" FF="-1" LUT="-1" fileDirectory="E:\FYP\HLS\MAC_SAP"><\/item>
<item  id="117" filename="fyp/PHY_DATA_confirm.c" linenumber="15" name="add_ln15" contextFuncName="phy_data_confirm" moduleName="send_frame" rtlName="add_ln15_fu_484_p2" latency="0" BRAM="-1" DSP="-1" FF="0" LUT="15" fileDirectory="E:\FYP\HLS\MAC_SAP"><\/item>
<item  id="118" filename="fyp/PHY_DATA_confirm.c" linenumber="16" name="icmp_ln16" contextFuncName="phy_data_confirm" moduleName="send_frame" rtlName="icmp_ln16_fu_490_p2" latency="0" BRAM="-1" DSP="-1" FF="0" LUT="11" fileDirectory="E:\FYP\HLS\MAC_SAP"><\/item>
<item  id="121" filename="fyp/PHY_DATA_confirm.c" linenumber="21" name="_ln21" contextFuncName="phy_data_confirm" moduleName="send_frame" rtlName="grp_phy_data_request_fu_422" latency="1" BRAM="-1" DSP="-1" FF="-1" LUT="-1" fileDirectory="E:\FYP\HLS\MAC_SAP"><\/item>
<item  id="124" filename="fyp/PHY_DATA_confirm.c" linenumber="17" name="_ln17" contextFuncName="phy_data_confirm" moduleName="send_frame" rtlName="call_ln17_phy_txend_request_fu_429" latency="0" BRAM="-1" DSP="-1" FF="-1" LUT="-1" fileDirectory="E:\FYP\HLS\MAC_SAP"><\/item>
<item  id="131" filename="fyp/mac_layer.c" linenumber="25" name="_ln25" contextFuncName="send_frame" moduleName="send_frame" rtlName="grp_phy_txend_confirm_fu_292" latency="1" BRAM="-1" DSP="-1" FF="-1" LUT="-1" fileDirectory="E:\FYP\HLS\MAC_SAP"><\/item>
<\/annotationInfo>
</annotationInfo>
