{
  "Top": "ma_unitdatax_request",
  "RtlTop": "ma_unitdatax_request",
  "RtlPrefix": "",
  "SourceLanguage": "c",
  "ResetStyle": "control",
  "GenerateBdFiles": "0",
  "HostMachineBits": "64",
  "Target": {
    "Family": "artix7",
    "Device": "xc7a35t",
    "Package": "-cpg236",
    "Speed": "-1"
  },
  "HlsSolution": {
    
  },
  "Args": {
    "source_addr": {
      "index": "0",
      "type": {
        "kinds": [
          "struct",
          "pointer"
        ],
        "dataType": "mac48",
        "structImpl": "flat-interface",
        "fields": {"mac": {
            "order": "0",
            "kinds": ["array"],
            "dataType": "unsigned",
            "dataWidth": "8",
            "arraySizes": ["6"],
            "multiInterfaceRef": [
              "source_addr_mac_address0",
              "source_addr_mac_address1",
              "source_addr_mac_d0",
              "source_addr_mac_d1",
              "source_addr_mac_q0",
              "source_addr_mac_q1"
            ],
            "structImpl": "interface"
          }}
      }
    },
    "dest_addr": {
      "index": "1",
      "type": {
        "kinds": [
          "struct",
          "pointer"
        ],
        "dataType": "mac48",
        "structImpl": "flat-interface",
        "fields": {"mac": {
            "order": "0",
            "kinds": ["array"],
            "dataType": "unsigned",
            "dataWidth": "8",
            "arraySizes": ["6"],
            "multiInterfaceRef": [
              "dest_addr_mac_address0",
              "dest_addr_mac_address1",
              "dest_addr_mac_d0",
              "dest_addr_mac_d1",
              "dest_addr_mac_q0",
              "dest_addr_mac_q1"
            ],
            "structImpl": "interface"
          }}
      }
    },
    "data": {
      "index": "2",
      "type": {
        "kinds": ["array"],
        "dataType": "unsigned",
        "dataWidth": "8",
        "arraySizes": ["70"],
        "multiInterfaceRef": [
          "data_address0",
          "data_q0"
        ]
      }
    },
    "up": {
      "index": "3",
      "type": {
        "dataType": "uint4",
        "dataWidth": "4",
        "interfaceRef": "up"
      }
    },
    "s_class": {
      "index": "4",
      "type": {
        "dataType": "service_class",
        "dataWidth": "1",
        "interfaceRef": "s_class"
      }
    },
    "c_identifier": {
      "index": "5",
      "type": {
        "kinds": ["struct"],
        "dataType": "channel_identifier",
        "structImpl": "flat-interface",
        "fields": {
          "operating_class": {
            "order": "0",
            "dataType": "unsigned",
            "dataWidth": "8",
            "interfaceRef": "c_identifier_operating_class",
            "structImpl": "field"
          },
          "channel_number": {
            "order": "1",
            "dataType": "unsigned",
            "dataWidth": "8",
            "interfaceRef": "c_identifier_channel_number",
            "structImpl": "field"
          }
        }
      }
    },
    "t_slot": {
      "index": "6",
      "type": {
        "kinds": ["pointer"],
        "dataType": "time_slot",
        "dataWidth": "2",
        "interfaceRef": "t_slot"
      }
    },
    "d_rate": {
      "index": "7",
      "type": {
        "kinds": ["pointer"],
        "dataType": "uint7",
        "dataWidth": "7",
        "interfaceRef": "d_rate"
      }
    },
    "tx_power_lvl": {
      "index": "8",
      "type": {
        "kinds": ["pointer"],
        "dataType": "uint4",
        "dataWidth": "4",
        "interfaceRef": "tx_power_lvl"
      }
    },
    "expiry_time": {
      "index": "9",
      "type": {
        "kinds": ["pointer"],
        "dataType": "long",
        "dataWidth": "64",
        "interfaceRef": "expiry_time"
      }
    }
  },
  "Return": {
    
  },
  "ClockInfo": {
    "ClockName": "ap_clk",
    "ClockPeriod": "10",
    "IsCombLogic": "0",
    "II": "x",
    "Latency": "1",
    "Uncertainty": "1.25"
  },
  "Xdc": {"OocClocks": ["create_clock -name ap_clk -period 10.000 [get_ports ap_clk]"]},
  "Ipx": {
    "Vendor": "xilinx.com",
    "Library": "hls",
    "Name": "ma_unitdatax_request",
    "Version": "1.0",
    "DisplayName": "Ma_unitdatax_request",
    "Revision": "",
    "Description": "An IP generated by Vivado HLS",
    "Taxonomy": "\/VIVADO_HLS_IP",
    "AutoFamilySupport": ""
  },
  "Files": {
    "CSource": [
      "..\/MA_UNITDATAX_request.c",
      "..\/compose_mac_frame.c",
      "..\/crc_32.c",
      "..\/crc_32_validate.c",
      "..\/decompose_mac_frame.c",
      "..\/edca.c",
      "..\/mac_layer.c",
      "..\/r_n_g.c",
      "..\/timer.c"
    ],
    "Vhdl": [
      "impl\/vhdl\/compose_mac_frame.vhd",
      "impl\/vhdl\/enqueue_dequeue_fbkb.vhd",
      "impl\/vhdl\/enqueue_dequeue_fram.vhd",
      "impl\/vhdl\/ma_unitdatax_requcud.vhd",
      "impl\/vhdl\/ma_unitdatax_requdEe.vhd",
      "impl\/vhdl\/ma_unitdatax_requeOg.vhd",
      "impl\/vhdl\/ma_unitdatax_request.vhd"
    ],
    "Verilog": [
      "impl\/verilog\/compose_mac_frame.v",
      "impl\/verilog\/enqueue_dequeue_fbkb.v",
      "impl\/verilog\/enqueue_dequeue_fbkb_ram.dat",
      "impl\/verilog\/enqueue_dequeue_fram.v",
      "impl\/verilog\/ma_unitdatax_requcud.v",
      "impl\/verilog\/ma_unitdatax_requdEe.v",
      "impl\/verilog\/ma_unitdatax_requeOg.v",
      "impl\/verilog\/ma_unitdatax_request.v"
    ],
    "Misc": ["impl\/misc\/logo.png"],
    "DesignXml": "E:\/FYP\/HLS\/MAC_SAP\/fyp\/solution1\/.autopilot\/db\/ma_unitdatax_request.design.xml",
    "DebugDir": "E:\/FYP\/HLS\/MAC_SAP\/fyp\/solution1\/.debug",
    "ProtoInst": [
      "E:\/FYP\/HLS\/MAC_SAP\/fyp\/solution1\/.debug\/add_to_queue.protoinst",
      "E:\/FYP\/HLS\/MAC_SAP\/fyp\/solution1\/.debug\/backoff_vi.protoinst",
      "E:\/FYP\/HLS\/MAC_SAP\/fyp\/solution1\/.debug\/backoff_vo.protoinst",
      "E:\/FYP\/HLS\/MAC_SAP\/fyp\/solution1\/.debug\/calc_crc.protoinst",
      "E:\/FYP\/HLS\/MAC_SAP\/fyp\/solution1\/.debug\/compose_mac_frame.protoinst",
      "E:\/FYP\/HLS\/MAC_SAP\/fyp\/solution1\/.debug\/compose_mac_header.protoinst",
      "E:\/FYP\/HLS\/MAC_SAP\/fyp\/solution1\/.debug\/decompose_mac_frame.protoinst",
      "E:\/FYP\/HLS\/MAC_SAP\/fyp\/solution1\/.debug\/dequeue_frame.protoinst",
      "E:\/FYP\/HLS\/MAC_SAP\/fyp\/solution1\/.debug\/enque.protoinst",
      "E:\/FYP\/HLS\/MAC_SAP\/fyp\/solution1\/.debug\/enqueue_dequeue_frame.protoinst",
      "E:\/FYP\/HLS\/MAC_SAP\/fyp\/solution1\/.debug\/enqueue_frame.protoinst",
      "E:\/FYP\/HLS\/MAC_SAP\/fyp\/solution1\/.debug\/enque_frame.protoinst",
      "E:\/FYP\/HLS\/MAC_SAP\/fyp\/solution1\/.debug\/ma_unitdatax_request.protoinst",
      "E:\/FYP\/HLS\/MAC_SAP\/fyp\/solution1\/.debug\/random_int_gen.protoinst",
      "E:\/FYP\/HLS\/MAC_SAP\/fyp\/solution1\/.debug\/reset_pointers.protoinst",
      "E:\/FYP\/HLS\/MAC_SAP\/fyp\/solution1\/.debug\/send_frame.protoinst",
      "E:\/FYP\/HLS\/MAC_SAP\/fyp\/solution1\/.debug\/slot_boundary_timing.protoinst",
      "E:\/FYP\/HLS\/MAC_SAP\/fyp\/solution1\/.debug\/start_backoff_vo.protoinst",
      "E:\/FYP\/HLS\/MAC_SAP\/fyp\/solution1\/.debug\/start_timer.protoinst",
      "E:\/FYP\/HLS\/MAC_SAP\/fyp\/solution1\/.debug\/stop_timer.protoinst",
      "E:\/FYP\/HLS\/MAC_SAP\/fyp\/solution1\/.debug\/validate_crc.protoinst"
    ]
  },
  "SubcoreInfo": {
    "HasXpmMemory": false,
    "HasClockedDsp": false,
    "IP": []
  },
  "Interfaces": {
    "ap_clk": {
      "type": "clock",
      "ctype": {"CLK": {"Type": "bool"}},
      "bundle_name": "ap_clk",
      "bundle_role": "default",
      "reset": "ap_rst"
    },
    "ap_ctrl": {
      "type": "ap_ctrl",
      "ctrl_ports": "ap_start ap_done ap_idle ap_ready",
      "ctype": {
        "start": {"Type": "bool"},
        "done": {"Type": "bool"},
        "idle": {"Type": "bool"},
        "ready": {"Type": "bool"}
      }
    },
    "ap_rst": {
      "type": "reset",
      "polarity": "ACTIVE_HIGH",
      "ctype": {"RST": {"Type": "bool"}},
      "bundle_name": "ap_rst",
      "bundle_role": "default"
    },
    "c_identifier_channel_number": {
      "type": "data",
      "dir": "in",
      "width": "8",
      "ctype": {"DATA": {
          "Type": "integer unsigned",
          "Width": "8"
        }},
      "bundle_name": "c_identifier_channel_number",
      "bundle_role": "default"
    },
    "c_identifier_operating_class": {
      "type": "data",
      "dir": "in",
      "width": "8",
      "ctype": {"DATA": {
          "Type": "integer unsigned",
          "Width": "8"
        }},
      "bundle_name": "c_identifier_operating_class",
      "bundle_role": "default"
    },
    "d_rate": {
      "type": "data",
      "dir": "in",
      "width": "7",
      "ctype": {"DATA": {
          "Type": "integer unsigned",
          "Width": "7"
        }},
      "bundle_name": "d_rate",
      "bundle_role": "default"
    },
    "data_address0": {
      "type": "data",
      "dir": "out",
      "width": "7",
      "ctype": {"DATA": {
          "Type": "null",
          "Width": "7"
        }},
      "bundle_name": "data",
      "bundle_role": "address0"
    },
    "data_q0": {
      "type": "data",
      "dir": "in",
      "width": "8",
      "ctype": {"DATA": {
          "Type": "integer unsigned",
          "Width": "8"
        }},
      "bundle_name": "data",
      "bundle_role": "q0"
    },
    "dest_addr_mac_address0": {
      "type": "data",
      "dir": "out",
      "width": "3",
      "ctype": {"DATA": {
          "Type": "null",
          "Width": "3"
        }},
      "bundle_name": "dest_addr_mac",
      "bundle_role": "address0"
    },
    "dest_addr_mac_address1": {
      "type": "data",
      "dir": "out",
      "width": "3",
      "ctype": {"DATA": {
          "Type": "null",
          "Width": "3"
        }},
      "bundle_name": "dest_addr_mac",
      "bundle_role": "address1"
    },
    "dest_addr_mac_d0": {
      "type": "data",
      "dir": "out",
      "width": "8",
      "ctype": {"DATA": {
          "Type": "integer unsigned",
          "Width": "8"
        }},
      "bundle_name": "dest_addr_mac",
      "bundle_role": "d0"
    },
    "dest_addr_mac_d1": {
      "type": "data",
      "dir": "out",
      "width": "8",
      "ctype": {"DATA": {
          "Type": "integer unsigned",
          "Width": "8"
        }},
      "bundle_name": "dest_addr_mac",
      "bundle_role": "d1"
    },
    "dest_addr_mac_q0": {
      "type": "data",
      "dir": "in",
      "width": "8",
      "ctype": {"DATA": {
          "Type": "integer unsigned",
          "Width": "8"
        }},
      "bundle_name": "dest_addr_mac",
      "bundle_role": "q0"
    },
    "dest_addr_mac_q1": {
      "type": "data",
      "dir": "in",
      "width": "8",
      "ctype": {"DATA": {
          "Type": "integer unsigned",
          "Width": "8"
        }},
      "bundle_name": "dest_addr_mac",
      "bundle_role": "q1"
    },
    "expiry_time": {
      "type": "data",
      "dir": "in",
      "width": "64",
      "ctype": {"DATA": {
          "Type": "integer signed",
          "Width": "64"
        }},
      "bundle_name": "expiry_time",
      "bundle_role": "default"
    },
    "s_class": {
      "type": "data",
      "dir": "in",
      "width": "1",
      "ctype": {"DATA": {
          "Type": "null",
          "Width": "1"
        }},
      "bundle_name": "s_class",
      "bundle_role": "default"
    },
    "source_addr_mac_address0": {
      "type": "data",
      "dir": "out",
      "width": "3",
      "ctype": {"DATA": {
          "Type": "null",
          "Width": "3"
        }},
      "bundle_name": "source_addr_mac",
      "bundle_role": "address0"
    },
    "source_addr_mac_address1": {
      "type": "data",
      "dir": "out",
      "width": "3",
      "ctype": {"DATA": {
          "Type": "null",
          "Width": "3"
        }},
      "bundle_name": "source_addr_mac",
      "bundle_role": "address1"
    },
    "source_addr_mac_d0": {
      "type": "data",
      "dir": "out",
      "width": "8",
      "ctype": {"DATA": {
          "Type": "integer unsigned",
          "Width": "8"
        }},
      "bundle_name": "source_addr_mac",
      "bundle_role": "d0"
    },
    "source_addr_mac_d1": {
      "type": "data",
      "dir": "out",
      "width": "8",
      "ctype": {"DATA": {
          "Type": "integer unsigned",
          "Width": "8"
        }},
      "bundle_name": "source_addr_mac",
      "bundle_role": "d1"
    },
    "source_addr_mac_q0": {
      "type": "data",
      "dir": "in",
      "width": "8",
      "ctype": {"DATA": {
          "Type": "integer unsigned",
          "Width": "8"
        }},
      "bundle_name": "source_addr_mac",
      "bundle_role": "q0"
    },
    "source_addr_mac_q1": {
      "type": "data",
      "dir": "in",
      "width": "8",
      "ctype": {"DATA": {
          "Type": "integer unsigned",
          "Width": "8"
        }},
      "bundle_name": "source_addr_mac",
      "bundle_role": "q1"
    },
    "t_slot": {
      "type": "data",
      "dir": "in",
      "width": "2",
      "ctype": {"DATA": {
          "Type": "null",
          "Width": "2"
        }},
      "bundle_name": "t_slot",
      "bundle_role": "default"
    },
    "tx_power_lvl": {
      "type": "data",
      "dir": "in",
      "width": "4",
      "ctype": {"DATA": {
          "Type": "integer unsigned",
          "Width": "4"
        }},
      "bundle_name": "tx_power_lvl",
      "bundle_role": "default"
    },
    "up": {
      "type": "data",
      "dir": "in",
      "width": "4",
      "ctype": {"DATA": {
          "Type": "integer unsigned",
          "Width": "4"
        }},
      "bundle_name": "up",
      "bundle_role": "default"
    }
  },
  "RtlPorts": {
    "ap_clk": {
      "dir": "in",
      "width": "1"
    },
    "ap_rst": {
      "dir": "in",
      "width": "1"
    },
    "ap_start": {
      "dir": "in",
      "width": "1"
    },
    "ap_done": {
      "dir": "out",
      "width": "1"
    },
    "ap_idle": {
      "dir": "out",
      "width": "1"
    },
    "ap_ready": {
      "dir": "out",
      "width": "1"
    },
    "source_addr_mac_address0": {
      "dir": "out",
      "width": "3"
    },
    "source_addr_mac_ce0": {
      "dir": "out",
      "width": "1"
    },
    "source_addr_mac_we0": {
      "dir": "out",
      "width": "1"
    },
    "source_addr_mac_d0": {
      "dir": "out",
      "width": "8"
    },
    "source_addr_mac_q0": {
      "dir": "in",
      "width": "8"
    },
    "source_addr_mac_address1": {
      "dir": "out",
      "width": "3"
    },
    "source_addr_mac_ce1": {
      "dir": "out",
      "width": "1"
    },
    "source_addr_mac_we1": {
      "dir": "out",
      "width": "1"
    },
    "source_addr_mac_d1": {
      "dir": "out",
      "width": "8"
    },
    "source_addr_mac_q1": {
      "dir": "in",
      "width": "8"
    },
    "dest_addr_mac_address0": {
      "dir": "out",
      "width": "3"
    },
    "dest_addr_mac_ce0": {
      "dir": "out",
      "width": "1"
    },
    "dest_addr_mac_we0": {
      "dir": "out",
      "width": "1"
    },
    "dest_addr_mac_d0": {
      "dir": "out",
      "width": "8"
    },
    "dest_addr_mac_q0": {
      "dir": "in",
      "width": "8"
    },
    "dest_addr_mac_address1": {
      "dir": "out",
      "width": "3"
    },
    "dest_addr_mac_ce1": {
      "dir": "out",
      "width": "1"
    },
    "dest_addr_mac_we1": {
      "dir": "out",
      "width": "1"
    },
    "dest_addr_mac_d1": {
      "dir": "out",
      "width": "8"
    },
    "dest_addr_mac_q1": {
      "dir": "in",
      "width": "8"
    },
    "data_address0": {
      "dir": "out",
      "width": "7"
    },
    "data_ce0": {
      "dir": "out",
      "width": "1"
    },
    "data_q0": {
      "dir": "in",
      "width": "8"
    },
    "up": {
      "dir": "in",
      "width": "4"
    },
    "s_class": {
      "dir": "in",
      "width": "1",
      "isVector": "true"
    },
    "c_identifier_operating_class": {
      "dir": "in",
      "width": "8"
    },
    "c_identifier_channel_number": {
      "dir": "in",
      "width": "8"
    },
    "t_slot": {
      "dir": "in",
      "width": "2"
    },
    "d_rate": {
      "dir": "in",
      "width": "7"
    },
    "tx_power_lvl": {
      "dir": "in",
      "width": "4"
    },
    "expiry_time": {
      "dir": "in",
      "width": "64"
    }
  },
  "ModuleInfo": {
    "Hierarchy": {
      "ModuleName": "ma_unitdatax_request",
      "Instances": [
        {
          "ModuleName": "enqueue_dequeue_fram",
          "InstanceName": "grp_enqueue_dequeue_fram_fu_243"
        },
        {
          "ModuleName": "compose_mac_frame",
          "InstanceName": "grp_compose_mac_frame_fu_271"
        }
      ]
    },
    "Info": {
      "compose_mac_frame": {
        "FunctionProtocol": "ap_ctrl_hs",
        "isTaskLevelControl": "1",
        "isPipelined": "0",
        "isCombinational": "0",
        "isOneStateSeq": "0"
      },
      "enqueue_dequeue_fram": {
        "FunctionProtocol": "ap_ctrl_hs",
        "isTaskLevelControl": "1",
        "isPipelined": "0",
        "isCombinational": "0",
        "isOneStateSeq": "0"
      },
      "ma_unitdatax_request": {
        "FunctionProtocol": "ap_ctrl_hs",
        "isTaskLevelControl": "1",
        "isPipelined": "0",
        "isCombinational": "0",
        "isOneStateSeq": "0"
      }
    },
    "Metrics": {
      "compose_mac_frame": {
        "Latency": {
          "LatencyBest": "1215",
          "LatencyAvg": "1215",
          "LatencyWorst": "1215",
          "PipelineII": "1215",
          "PipelineDepth": "",
          "PipelineType": "none"
        },
        "Timing": {
          "Target": "10.00",
          "Uncertainty": "1.25",
          "Estimate": "6.316"
        },
        "Loops": [
          {
            "Name": "Loop 1",
            "TripCount": "70",
            "Latency": "140",
            "PipelineII": "",
            "PipelineDepth": "2"
          },
          {
            "Name": "char_array_loop",
            "TripCount": "96",
            "Latency": "1056",
            "PipelineII": "",
            "PipelineDepth": "11",
            "Loops": [{
                "Name": "iter_through_byte_loop",
                "TripCount": "8",
                "Latency": "8",
                "PipelineII": "",
                "PipelineDepth": "1"
              }]
          },
          {
            "Name": "Loop 3",
            "TripCount": "4",
            "Latency": "4",
            "PipelineII": "",
            "PipelineDepth": "1"
          }
        ],
        "Area": {
          "FF": "118",
          "LUT": "723",
          "BRAM_18K": "0",
          "DSP48E": "0",
          "URAM": "0"
        }
      },
      "enqueue_dequeue_fram": {
        "Latency": {
          "LatencyBest": "1",
          "LatencyAvg": "102",
          "LatencyWorst": "202",
          "PipelineIIMin": "1",
          "PipelineIIMax": "202",
          "PipelineII": "1 ~ 202",
          "PipelineDepth": "",
          "PipelineType": "none"
        },
        "Timing": {
          "Target": "10.00",
          "Uncertainty": "1.25",
          "Estimate": "5.486"
        },
        "Loops": [
          {
            "Name": "write_to_bk",
            "TripCount": "100",
            "Latency": "200",
            "PipelineII": "",
            "PipelineDepth": "2"
          },
          {
            "Name": "write_to_be",
            "TripCount": "100",
            "Latency": "200",
            "PipelineII": "",
            "PipelineDepth": "2"
          },
          {
            "Name": "write_to_vi",
            "TripCount": "100",
            "Latency": "200",
            "PipelineII": "",
            "PipelineDepth": "2"
          },
          {
            "Name": "write_to_vo",
            "TripCount": "100",
            "Latency": "200",
            "PipelineII": "",
            "PipelineDepth": "2"
          }
        ],
        "Area": {
          "BRAM_18K": "1",
          "DSP48E": "0",
          "FF": "172",
          "LUT": "661",
          "URAM": "0"
        }
      },
      "ma_unitdatax_request": {
        "Latency": {
          "LatencyBest": "1",
          "LatencyAvg": "1088",
          "LatencyWorst": "1563",
          "PipelineIIMin": "2",
          "PipelineIIMax": "1564",
          "PipelineII": "2 ~ 1564",
          "PipelineDepth": "",
          "PipelineType": "none"
        },
        "Timing": {
          "Target": "10.00",
          "Uncertainty": "1.25",
          "Estimate": "7.180"
        },
        "Loops": [{
            "Name": "Loop 1",
            "TripCount": "70",
            "Latency": "140",
            "PipelineII": "",
            "PipelineDepth": "2"
          }],
        "Area": {
          "BRAM_18K": "2",
          "DSP48E": "8",
          "FF": "862",
          "LUT": "2737",
          "URAM": "0"
        }
      }
    }
  },
  "Sdx": {
    "Target": "none",
    "ProfileOption": "0",
    "ProfileType": "none",
    "XO": "",
    "KernelName": "ma_unitdatax_request",
    "EnableXoSwEmu": "1"
  },
  "GenData": {
    "DataVersion": "0.2",
    "Time": "2020-10-30 21:10:58 +0530",
    "ToolName": "vivado_hls",
    "ToolVersion": "2019.2"
  }
}
